<?xml version="1.0" encoding="UTF-8"?>
<export version="E">
  <design>
    <source>/home/alex/PlaygroundCode/basic_microcontroller/basic_microcontroller.kicad_sch</source>
    <date>Tue 18 Jul 2023 04:22:47 PM CDT</date>
    <tool>Eeschema 7.0.6-7.0.6~ubuntu20.04.1</tool>
    <sheet number="1" name="/" tstamps="/">
      <title_block>
        <title/>
        <company/>
        <rev/>
        <date/>
        <source>basic_microcontroller.kicad_sch</source>
        <comment number="1" value=""/>
        <comment number="2" value=""/>
        <comment number="3" value=""/>
        <comment number="4" value=""/>
        <comment number="5" value=""/>
        <comment number="6" value=""/>
        <comment number="7" value=""/>
        <comment number="8" value=""/>
        <comment number="9" value=""/>
      </title_block>
    </sheet>
  </design>
  <components>
    <comp ref="C1">
      <value>20pF</value>
      <footprint>Capacitor_SMD:C_0603_1608Metric_Pad1.08x0.95mm_HandSolder</footprint>
      <datasheet>https://www.mouser.com/ProductDetail/80-CBR06C200J5GAUTO</datasheet>
      <libsource lib="Device" part="C" description="Unpolarized capacitor"/>
      <property name="Sheetname" value=""/>
      <property name="Sheetfile" value="basic_microcontroller.kicad_sch"/>
      <property name="ki_description" value="Unpolarized capacitor"/>
      <property name="ki_keywords" value="cap capacitor"/>
      <sheetpath names="/" tstamps="/"/>
      <tstamps>a204bd18-98ee-4f91-a390-b560be5a4da0</tstamps>
    </comp>
    <comp ref="C2">
      <value>20pF</value>
      <footprint>Capacitor_SMD:C_0603_1608Metric_Pad1.08x0.95mm_HandSolder</footprint>
      <datasheet>https://www.mouser.com/ProductDetail/80-CBR06C200J5GAUTO</datasheet>
      <libsource lib="Device" part="C" description="Unpolarized capacitor"/>
      <property name="Sheetname" value=""/>
      <property name="Sheetfile" value="basic_microcontroller.kicad_sch"/>
      <property name="ki_description" value="Unpolarized capacitor"/>
      <property name="ki_keywords" value="cap capacitor"/>
      <sheetpath names="/" tstamps="/"/>
      <tstamps>f5ff9913-a5fe-4c10-bbca-9f6ed71423da</tstamps>
    </comp>
    <comp ref="C3">
      <value>1uF</value>
      <footprint>Capacitor_SMD:C_0603_1608Metric_Pad1.08x0.95mm_HandSolder</footprint>
      <datasheet>https://www.mouser.com/ProductDetail/810-CGA3E1X7R1C105AC</datasheet>
      <libsource lib="Device" part="C" description="Unpolarized capacitor"/>
      <property name="Sheetname" value=""/>
      <property name="Sheetfile" value="basic_microcontroller.kicad_sch"/>
      <property name="ki_description" value="Unpolarized capacitor"/>
      <property name="ki_keywords" value="cap capacitor"/>
      <sheetpath names="/" tstamps="/"/>
      <tstamps>0dbe6fbb-e2d2-442c-8751-d3b3e1d7e588</tstamps>
    </comp>
    <comp ref="C4">
      <value>100nF</value>
      <footprint>Capacitor_SMD:C_0603_1608Metric_Pad1.08x0.95mm_HandSolder</footprint>
      <datasheet>https://www.mouser.com/ProductDetail/81-GCM188R71C104KA7J</datasheet>
      <libsource lib="Device" part="C" description="Unpolarized capacitor"/>
      <property name="Sheetname" value=""/>
      <property name="Sheetfile" value="basic_microcontroller.kicad_sch"/>
      <property name="ki_description" value="Unpolarized capacitor"/>
      <property name="ki_keywords" value="cap capacitor"/>
      <sheetpath names="/" tstamps="/"/>
      <tstamps>492749ca-ba63-48f1-ac51-834dbae27c06</tstamps>
    </comp>
    <comp ref="C5">
      <value>100nF</value>
      <footprint>Capacitor_SMD:C_0603_1608Metric_Pad1.08x0.95mm_HandSolder</footprint>
      <datasheet>https://www.mouser.com/ProductDetail/81-GCM188R71C104KA7J</datasheet>
      <libsource lib="Device" part="C" description="Unpolarized capacitor"/>
      <property name="Sheetname" value=""/>
      <property name="Sheetfile" value="basic_microcontroller.kicad_sch"/>
      <property name="ki_description" value="Unpolarized capacitor"/>
      <property name="ki_keywords" value="cap capacitor"/>
      <sheetpath names="/" tstamps="/"/>
      <tstamps>e16fbc67-6c85-4855-a045-c27c02c88a4b</tstamps>
    </comp>
    <comp ref="C6">
      <value>Stemma</value>
      <footprint>basic_microcontroller:stemma</footprint>
      <datasheet>https://www.mouser.dk/datasheet/2/737/4389_C13924-001_CCP-W20-03-BK-SMT-R-A-1708610.pdf</datasheet>
      <fields>
        <field name="Height">6.85</field>
        <field name="Manufacturer_Name">Adafruit</field>
        <field name="Manufacturer_Part_Number">4392</field>
        <field name="Mouser Part Number">485-4392</field>
        <field name="Mouser Price/Stock">https://www.mouser.co.uk/ProductDetail/Adafruit/4392?qs=xZ%2FP%252Ba9zWqbG2TKb%252Bnxciw%3D%3D</field>
      </fields>
      <libsource lib="basic_microcontroller" part="Stemma" description="Adafruit Accessories JST PH 4-pin Horizontal Connector (10-pack) - STEMMA"/>
      <property name="Height" value="6.85"/>
      <property name="Mouser Part Number" value="485-4392"/>
      <property name="Mouser Price/Stock" value="https://www.mouser.co.uk/ProductDetail/Adafruit/4392?qs=xZ%2FP%252Ba9zWqbG2TKb%252Bnxciw%3D%3D"/>
      <property name="Manufacturer_Name" value="Adafruit"/>
      <property name="Manufacturer_Part_Number" value="4392"/>
      <property name="Sheetname" value=""/>
      <property name="Sheetfile" value="basic_microcontroller.kicad_sch"/>
      <property name="ki_description" value="Adafruit Accessories JST PH 4-pin Horizontal Connector (10-pack) - STEMMA"/>
      <sheetpath names="/" tstamps="/"/>
      <tstamps>4f69634b-4fea-4f64-886b-d2819b3cdb04</tstamps>
    </comp>
    <comp ref="C7">
      <value>100nF</value>
      <footprint>Capacitor_SMD:C_0603_1608Metric_Pad1.08x0.95mm_HandSolder</footprint>
      <datasheet>https://www.mouser.com/ProductDetail/81-GCM188R71C104KA7J</datasheet>
      <libsource lib="Device" part="C" description="Unpolarized capacitor"/>
      <property name="Sheetname" value=""/>
      <property name="Sheetfile" value="basic_microcontroller.kicad_sch"/>
      <property name="ki_description" value="Unpolarized capacitor"/>
      <property name="ki_keywords" value="cap capacitor"/>
      <sheetpath names="/" tstamps="/"/>
      <tstamps>255088a9-1a07-4e1d-a49d-a5cd0d0e9d66</tstamps>
    </comp>
    <comp ref="C8">
      <value>100nF</value>
      <footprint>Capacitor_SMD:C_0603_1608Metric_Pad1.08x0.95mm_HandSolder</footprint>
      <datasheet>https://www.mouser.com/ProductDetail/81-GCM188R71C104KA7J</datasheet>
      <libsource lib="Device" part="C" description="Unpolarized capacitor"/>
      <property name="Sheetname" value=""/>
      <property name="Sheetfile" value="basic_microcontroller.kicad_sch"/>
      <property name="ki_description" value="Unpolarized capacitor"/>
      <property name="ki_keywords" value="cap capacitor"/>
      <sheetpath names="/" tstamps="/"/>
      <tstamps>5ab135d6-d45c-41c3-bb43-f7185b63ae35</tstamps>
    </comp>
    <comp ref="D1">
      <value>LED</value>
      <footprint>LED_SMD:LED_0805_2012Metric_Pad1.15x1.40mm_HandSolder</footprint>
      <datasheet>https://www.mouser.com/ProductDetail/ams-OSRAM/LG-R971-KN-1?qs=LsPilcdHE7EX1EB7GCLHxg%3D%3D</datasheet>
      <libsource lib="Device" part="LED" description="Light emitting diode"/>
      <property name="Sheetname" value=""/>
      <property name="Sheetfile" value="basic_microcontroller.kicad_sch"/>
      <property name="ki_description" value="Light emitting diode"/>
      <property name="ki_keywords" value="LED diode"/>
      <sheetpath names="/" tstamps="/"/>
      <tstamps>8ae66171-ed61-41f0-86ac-d9eda493edd2</tstamps>
    </comp>
    <comp ref="D2">
      <value>LED</value>
      <footprint>LED_SMD:LED_0805_2012Metric_Pad1.15x1.40mm_HandSolder</footprint>
      <datasheet>https://www.mouser.com/ProductDetail/ams-OSRAM/LG-R971-KN-1?qs=LsPilcdHE7EX1EB7GCLHxg%3D%3D</datasheet>
      <libsource lib="Device" part="LED" description="Light emitting diode"/>
      <property name="Sheetname" value=""/>
      <property name="Sheetfile" value="basic_microcontroller.kicad_sch"/>
      <property name="ki_description" value="Light emitting diode"/>
      <property name="ki_keywords" value="LED diode"/>
      <sheetpath names="/" tstamps="/"/>
      <tstamps>2b81bd03-bbf0-4e92-b999-6cb2fb5b8984</tstamps>
    </comp>
    <comp ref="D3">
      <value>LED</value>
      <footprint>LED_SMD:LED_0805_2012Metric_Pad1.15x1.40mm_HandSolder</footprint>
      <datasheet>https://www.mouser.com/ProductDetail/ams-OSRAM/LG-R971-KN-1?qs=LsPilcdHE7EX1EB7GCLHxg%3D%3D</datasheet>
      <libsource lib="Device" part="LED" description="Light emitting diode"/>
      <property name="Sheetname" value=""/>
      <property name="Sheetfile" value="basic_microcontroller.kicad_sch"/>
      <property name="ki_description" value="Light emitting diode"/>
      <property name="ki_keywords" value="LED diode"/>
      <sheetpath names="/" tstamps="/"/>
      <tstamps>7c9dcab1-fe5f-458f-b832-49ceac7a7a1e</tstamps>
    </comp>
    <comp ref="D4">
      <value>LED</value>
      <footprint>LED_SMD:LED_0805_2012Metric_Pad1.15x1.40mm_HandSolder</footprint>
      <datasheet>https://www.mouser.com/ProductDetail/ams-OSRAM/LG-R971-KN-1?qs=LsPilcdHE7EX1EB7GCLHxg%3D%3D</datasheet>
      <libsource lib="Device" part="LED" description="Light emitting diode"/>
      <property name="Sheetname" value=""/>
      <property name="Sheetfile" value="basic_microcontroller.kicad_sch"/>
      <property name="ki_description" value="Light emitting diode"/>
      <property name="ki_keywords" value="LED diode"/>
      <sheetpath names="/" tstamps="/"/>
      <tstamps>7aa336b9-cc4f-4c2f-8da7-a8fec9cd5923</tstamps>
    </comp>
    <comp ref="D5">
      <value>LED</value>
      <footprint>LED_SMD:LED_0805_2012Metric_Pad1.15x1.40mm_HandSolder</footprint>
      <datasheet>https://www.mouser.com/ProductDetail/ams-OSRAM/LG-R971-KN-1?qs=LsPilcdHE7EX1EB7GCLHxg%3D%3D</datasheet>
      <libsource lib="Device" part="LED" description="Light emitting diode"/>
      <property name="Sheetname" value=""/>
      <property name="Sheetfile" value="basic_microcontroller.kicad_sch"/>
      <property name="ki_description" value="Light emitting diode"/>
      <property name="ki_keywords" value="LED diode"/>
      <sheetpath names="/" tstamps="/"/>
      <tstamps>693aa9e0-1fd0-4609-946a-8b27161db737</tstamps>
    </comp>
    <comp ref="D6">
      <value>LED</value>
      <footprint>LED_SMD:LED_0805_2012Metric_Pad1.15x1.40mm_HandSolder</footprint>
      <datasheet>https://www.mouser.com/ProductDetail/ams-OSRAM/LG-R971-KN-1?qs=LsPilcdHE7EX1EB7GCLHxg%3D%3D</datasheet>
      <libsource lib="Device" part="LED" description="Light emitting diode"/>
      <property name="Sheetname" value=""/>
      <property name="Sheetfile" value="basic_microcontroller.kicad_sch"/>
      <property name="ki_description" value="Light emitting diode"/>
      <property name="ki_keywords" value="LED diode"/>
      <sheetpath names="/" tstamps="/"/>
      <tstamps>39d736cf-76ee-413e-a2ab-849684220992</tstamps>
    </comp>
    <comp ref="D7">
      <value>LED</value>
      <footprint>LED_SMD:LED_0805_2012Metric_Pad1.15x1.40mm_HandSolder</footprint>
      <datasheet>https://www.mouser.com/ProductDetail/ams-OSRAM/LG-R971-KN-1?qs=LsPilcdHE7EX1EB7GCLHxg%3D%3D</datasheet>
      <libsource lib="Device" part="LED" description="Light emitting diode"/>
      <property name="Sheetname" value=""/>
      <property name="Sheetfile" value="basic_microcontroller.kicad_sch"/>
      <property name="ki_description" value="Light emitting diode"/>
      <property name="ki_keywords" value="LED diode"/>
      <sheetpath names="/" tstamps="/"/>
      <tstamps>4d14ee41-a96a-4817-a67d-3e44d18367ef</tstamps>
    </comp>
    <comp ref="D8">
      <value>LED</value>
      <footprint>LED_SMD:LED_0805_2012Metric_Pad1.15x1.40mm_HandSolder</footprint>
      <datasheet>https://www.mouser.com/ProductDetail/ams-OSRAM/LG-R971-KN-1?qs=LsPilcdHE7EX1EB7GCLHxg%3D%3D</datasheet>
      <libsource lib="Device" part="LED" description="Light emitting diode"/>
      <property name="Sheetname" value=""/>
      <property name="Sheetfile" value="basic_microcontroller.kicad_sch"/>
      <property name="ki_description" value="Light emitting diode"/>
      <property name="ki_keywords" value="LED diode"/>
      <sheetpath names="/" tstamps="/"/>
      <tstamps>c69e4c5b-b758-4e5e-b96c-f1f3f6a7fc53</tstamps>
    </comp>
    <comp ref="D9">
      <value>LED</value>
      <footprint>LED_SMD:LED_0805_2012Metric_Pad1.15x1.40mm_HandSolder</footprint>
      <datasheet>https://www.mouser.com/ProductDetail/ams-OSRAM/LG-R971-KN-1?qs=LsPilcdHE7EX1EB7GCLHxg%3D%3D</datasheet>
      <libsource lib="Device" part="LED" description="Light emitting diode"/>
      <property name="Sheetname" value=""/>
      <property name="Sheetfile" value="basic_microcontroller.kicad_sch"/>
      <property name="ki_description" value="Light emitting diode"/>
      <property name="ki_keywords" value="LED diode"/>
      <sheetpath names="/" tstamps="/"/>
      <tstamps>5eb56ed2-6300-4664-bb25-8ee345c4a8ad</tstamps>
    </comp>
    <comp ref="D10">
      <value>LED</value>
      <footprint>LED_SMD:LED_0805_2012Metric_Pad1.15x1.40mm_HandSolder</footprint>
      <datasheet>https://www.mouser.com/ProductDetail/ams-OSRAM/LG-R971-KN-1?qs=LsPilcdHE7EX1EB7GCLHxg%3D%3D</datasheet>
      <libsource lib="Device" part="LED" description="Light emitting diode"/>
      <property name="Sheetname" value=""/>
      <property name="Sheetfile" value="basic_microcontroller.kicad_sch"/>
      <property name="ki_description" value="Light emitting diode"/>
      <property name="ki_keywords" value="LED diode"/>
      <sheetpath names="/" tstamps="/"/>
      <tstamps>db03ef5b-8e5e-410e-8326-9854d739bca1</tstamps>
    </comp>
    <comp ref="D11">
      <value>LED</value>
      <footprint>LED_SMD:LED_0805_2012Metric_Pad1.15x1.40mm_HandSolder</footprint>
      <datasheet>https://www.mouser.com/ProductDetail/ams-OSRAM/LG-R971-KN-1?qs=LsPilcdHE7EX1EB7GCLHxg%3D%3D</datasheet>
      <libsource lib="Device" part="LED" description="Light emitting diode"/>
      <property name="Sheetname" value=""/>
      <property name="Sheetfile" value="basic_microcontroller.kicad_sch"/>
      <property name="ki_description" value="Light emitting diode"/>
      <property name="ki_keywords" value="LED diode"/>
      <sheetpath names="/" tstamps="/"/>
      <tstamps>f3688c00-3b4e-4992-bc6f-9eafd260efb9</tstamps>
    </comp>
    <comp ref="D12">
      <value>LED</value>
      <footprint>LED_SMD:LED_0805_2012Metric_Pad1.15x1.40mm_HandSolder</footprint>
      <datasheet>https://www.mouser.com/ProductDetail/ams-OSRAM/LG-R971-KN-1?qs=LsPilcdHE7EX1EB7GCLHxg%3D%3D</datasheet>
      <libsource lib="Device" part="LED" description="Light emitting diode"/>
      <property name="Sheetname" value=""/>
      <property name="Sheetfile" value="basic_microcontroller.kicad_sch"/>
      <property name="ki_description" value="Light emitting diode"/>
      <property name="ki_keywords" value="LED diode"/>
      <sheetpath names="/" tstamps="/"/>
      <tstamps>86e0460c-116d-4d4e-ad1c-c8e9427e7f28</tstamps>
    </comp>
    <comp ref="D13">
      <value>LED</value>
      <footprint>LED_SMD:LED_0805_2012Metric_Pad1.15x1.40mm_HandSolder</footprint>
      <datasheet>https://www.mouser.com/ProductDetail/ams-OSRAM/LG-R971-KN-1?qs=LsPilcdHE7EX1EB7GCLHxg%3D%3D</datasheet>
      <libsource lib="Device" part="LED" description="Light emitting diode"/>
      <property name="Sheetname" value=""/>
      <property name="Sheetfile" value="basic_microcontroller.kicad_sch"/>
      <property name="ki_description" value="Light emitting diode"/>
      <property name="ki_keywords" value="LED diode"/>
      <sheetpath names="/" tstamps="/"/>
      <tstamps>fa658bd5-a734-4715-a489-ff2013e4cce4</tstamps>
    </comp>
    <comp ref="D14">
      <value>LED</value>
      <footprint>LED_SMD:LED_0805_2012Metric_Pad1.15x1.40mm_HandSolder</footprint>
      <datasheet>https://www.mouser.com/ProductDetail/ams-OSRAM/LG-R971-KN-1?qs=LsPilcdHE7EX1EB7GCLHxg%3D%3D</datasheet>
      <libsource lib="Device" part="LED" description="Light emitting diode"/>
      <property name="Sheetname" value=""/>
      <property name="Sheetfile" value="basic_microcontroller.kicad_sch"/>
      <property name="ki_description" value="Light emitting diode"/>
      <property name="ki_keywords" value="LED diode"/>
      <sheetpath names="/" tstamps="/"/>
      <tstamps>5299a227-b946-488c-87d6-7e48a3def573</tstamps>
    </comp>
    <comp ref="D15">
      <value>LED</value>
      <footprint>LED_SMD:LED_0805_2012Metric_Pad1.15x1.40mm_HandSolder</footprint>
      <datasheet>https://www.mouser.com/ProductDetail/ams-OSRAM/LG-R971-KN-1?qs=LsPilcdHE7EX1EB7GCLHxg%3D%3D</datasheet>
      <libsource lib="Device" part="LED" description="Light emitting diode"/>
      <property name="Sheetname" value=""/>
      <property name="Sheetfile" value="basic_microcontroller.kicad_sch"/>
      <property name="ki_description" value="Light emitting diode"/>
      <property name="ki_keywords" value="LED diode"/>
      <sheetpath names="/" tstamps="/"/>
      <tstamps>ebb2207d-5524-46cd-89bf-bcf546a0cb84</tstamps>
    </comp>
    <comp ref="D16">
      <value>LED</value>
      <footprint>LED_SMD:LED_0805_2012Metric_Pad1.15x1.40mm_HandSolder</footprint>
      <datasheet>https://www.mouser.com/ProductDetail/ams-OSRAM/LG-R971-KN-1?qs=LsPilcdHE7EX1EB7GCLHxg%3D%3D</datasheet>
      <libsource lib="Device" part="LED" description="Light emitting diode"/>
      <property name="Sheetname" value=""/>
      <property name="Sheetfile" value="basic_microcontroller.kicad_sch"/>
      <property name="ki_description" value="Light emitting diode"/>
      <property name="ki_keywords" value="LED diode"/>
      <sheetpath names="/" tstamps="/"/>
      <tstamps>a8ed3055-e8c8-4760-8cd0-85e5e9db1a9a</tstamps>
    </comp>
    <comp ref="D17">
      <value>LED</value>
      <footprint>LED_SMD:LED_0805_2012Metric_Pad1.15x1.40mm_HandSolder</footprint>
      <datasheet>https://www.mouser.com/ProductDetail/ams-OSRAM/LG-R971-KN-1?qs=LsPilcdHE7EX1EB7GCLHxg%3D%3D</datasheet>
      <libsource lib="Device" part="LED" description="Light emitting diode"/>
      <property name="Sheetname" value=""/>
      <property name="Sheetfile" value="basic_microcontroller.kicad_sch"/>
      <property name="ki_description" value="Light emitting diode"/>
      <property name="ki_keywords" value="LED diode"/>
      <sheetpath names="/" tstamps="/"/>
      <tstamps>e1cc259e-e926-467c-80f8-dadbda5f60d8</tstamps>
    </comp>
    <comp ref="D18">
      <value>LED</value>
      <footprint>LED_SMD:LED_0805_2012Metric_Pad1.15x1.40mm_HandSolder</footprint>
      <datasheet>https://www.mouser.com/ProductDetail/ams-OSRAM/LG-R971-KN-1?qs=LsPilcdHE7EX1EB7GCLHxg%3D%3D</datasheet>
      <libsource lib="Device" part="LED" description="Light emitting diode"/>
      <property name="Sheetname" value=""/>
      <property name="Sheetfile" value="basic_microcontroller.kicad_sch"/>
      <property name="ki_description" value="Light emitting diode"/>
      <property name="ki_keywords" value="LED diode"/>
      <sheetpath names="/" tstamps="/"/>
      <tstamps>8cc064c7-3326-4f18-8d85-2a02cc05fe19</tstamps>
    </comp>
    <comp ref="D19">
      <value>LED</value>
      <footprint>LED_SMD:LED_0805_2012Metric_Pad1.15x1.40mm_HandSolder</footprint>
      <datasheet>https://www.mouser.com/ProductDetail/ams-OSRAM/LG-R971-KN-1?qs=LsPilcdHE7EX1EB7GCLHxg%3D%3D</datasheet>
      <libsource lib="Device" part="LED" description="Light emitting diode"/>
      <property name="Sheetname" value=""/>
      <property name="Sheetfile" value="basic_microcontroller.kicad_sch"/>
      <property name="ki_description" value="Light emitting diode"/>
      <property name="ki_keywords" value="LED diode"/>
      <sheetpath names="/" tstamps="/"/>
      <tstamps>3f5cd1e9-c6ed-4816-9356-08a276b606b0</tstamps>
    </comp>
    <comp ref="D20">
      <value>LED</value>
      <footprint>LED_SMD:LED_0805_2012Metric_Pad1.15x1.40mm_HandSolder</footprint>
      <datasheet>https://www.mouser.com/ProductDetail/ams-OSRAM/LG-R971-KN-1?qs=LsPilcdHE7EX1EB7GCLHxg%3D%3D</datasheet>
      <libsource lib="Device" part="LED" description="Light emitting diode"/>
      <property name="Sheetname" value=""/>
      <property name="Sheetfile" value="basic_microcontroller.kicad_sch"/>
      <property name="ki_description" value="Light emitting diode"/>
      <property name="ki_keywords" value="LED diode"/>
      <sheetpath names="/" tstamps="/"/>
      <tstamps>583bb7ca-38c4-4d46-888a-b2b9e2ba5062</tstamps>
    </comp>
    <comp ref="D21">
      <value>LED</value>
      <footprint>LED_SMD:LED_0805_2012Metric_Pad1.15x1.40mm_HandSolder</footprint>
      <datasheet>https://www.mouser.com/ProductDetail/ams-OSRAM/LG-R971-KN-1?qs=LsPilcdHE7EX1EB7GCLHxg%3D%3D</datasheet>
      <libsource lib="Device" part="LED" description="Light emitting diode"/>
      <property name="Sheetname" value=""/>
      <property name="Sheetfile" value="basic_microcontroller.kicad_sch"/>
      <property name="ki_description" value="Light emitting diode"/>
      <property name="ki_keywords" value="LED diode"/>
      <sheetpath names="/" tstamps="/"/>
      <tstamps>0bf7cb95-7a89-404e-88b7-ce1db980bbe5</tstamps>
    </comp>
    <comp ref="D22">
      <value>LED</value>
      <footprint>LED_SMD:LED_0805_2012Metric_Pad1.15x1.40mm_HandSolder</footprint>
      <datasheet>https://www.mouser.com/ProductDetail/ams-OSRAM/LG-R971-KN-1?qs=LsPilcdHE7EX1EB7GCLHxg%3D%3D</datasheet>
      <libsource lib="Device" part="LED" description="Light emitting diode"/>
      <property name="Sheetname" value=""/>
      <property name="Sheetfile" value="basic_microcontroller.kicad_sch"/>
      <property name="ki_description" value="Light emitting diode"/>
      <property name="ki_keywords" value="LED diode"/>
      <sheetpath names="/" tstamps="/"/>
      <tstamps>e917b4d9-9102-4959-8be1-d28bb250236c</tstamps>
    </comp>
    <comp ref="D23">
      <value>LED</value>
      <footprint>LED_SMD:LED_0805_2012Metric_Pad1.15x1.40mm_HandSolder</footprint>
      <datasheet>https://www.mouser.com/ProductDetail/ams-OSRAM/LG-R971-KN-1?qs=LsPilcdHE7EX1EB7GCLHxg%3D%3D</datasheet>
      <libsource lib="Device" part="LED" description="Light emitting diode"/>
      <property name="Sheetname" value=""/>
      <property name="Sheetfile" value="basic_microcontroller.kicad_sch"/>
      <property name="ki_description" value="Light emitting diode"/>
      <property name="ki_keywords" value="LED diode"/>
      <sheetpath names="/" tstamps="/"/>
      <tstamps>9d6bcb4e-8aec-4fb0-aace-23c5ced3ce8f</tstamps>
    </comp>
    <comp ref="D24">
      <value>LED</value>
      <footprint>LED_SMD:LED_0805_2012Metric_Pad1.15x1.40mm_HandSolder</footprint>
      <datasheet>https://www.mouser.com/ProductDetail/ams-OSRAM/LG-R971-KN-1?qs=LsPilcdHE7EX1EB7GCLHxg%3D%3D</datasheet>
      <libsource lib="Device" part="LED" description="Light emitting diode"/>
      <property name="Sheetname" value=""/>
      <property name="Sheetfile" value="basic_microcontroller.kicad_sch"/>
      <property name="ki_description" value="Light emitting diode"/>
      <property name="ki_keywords" value="LED diode"/>
      <sheetpath names="/" tstamps="/"/>
      <tstamps>97a36880-2d24-465d-bb91-b952ddd9441d</tstamps>
    </comp>
    <comp ref="D25">
      <value>LED</value>
      <footprint>LED_SMD:LED_0805_2012Metric_Pad1.15x1.40mm_HandSolder</footprint>
      <datasheet>https://www.mouser.com/ProductDetail/ams-OSRAM/LG-R971-KN-1?qs=LsPilcdHE7EX1EB7GCLHxg%3D%3D</datasheet>
      <libsource lib="Device" part="LED" description="Light emitting diode"/>
      <property name="Sheetname" value=""/>
      <property name="Sheetfile" value="basic_microcontroller.kicad_sch"/>
      <property name="ki_description" value="Light emitting diode"/>
      <property name="ki_keywords" value="LED diode"/>
      <sheetpath names="/" tstamps="/"/>
      <tstamps>7ed0c5af-6139-49c2-9bbb-0a8fc7005846</tstamps>
    </comp>
    <comp ref="D26">
      <value>LED</value>
      <footprint>LED_SMD:LED_0805_2012Metric_Pad1.15x1.40mm_HandSolder</footprint>
      <datasheet>https://www.mouser.com/ProductDetail/ams-OSRAM/LG-R971-KN-1?qs=LsPilcdHE7EX1EB7GCLHxg%3D%3D</datasheet>
      <libsource lib="Device" part="LED" description="Light emitting diode"/>
      <property name="Sheetname" value=""/>
      <property name="Sheetfile" value="basic_microcontroller.kicad_sch"/>
      <property name="ki_description" value="Light emitting diode"/>
      <property name="ki_keywords" value="LED diode"/>
      <sheetpath names="/" tstamps="/"/>
      <tstamps>e8adfdfd-bded-4aad-abcb-e49b31f63cae</tstamps>
    </comp>
    <comp ref="D27">
      <value>LED_ABRG</value>
      <footprint>basic_microcontroller:RGB LED</footprint>
      <datasheet>https://www.mouser.com/ProductDetail/Inolux/IN-S85TATRGB?qs=fAHHVMwC%252BbjTv4T6LB3H6Q%3D%3D</datasheet>
      <libsource lib="Device" part="LED_ABRG" description="RGB LED, anode/blue/red/green"/>
      <property name="Sheetname" value=""/>
      <property name="Sheetfile" value="basic_microcontroller.kicad_sch"/>
      <property name="ki_description" value="RGB LED, anode/blue/red/green"/>
      <property name="ki_keywords" value="LED RGB diode"/>
      <sheetpath names="/" tstamps="/"/>
      <tstamps>3429a592-69e0-4819-8e96-a33c037cdb7b</tstamps>
    </comp>
    <comp ref="D28">
      <value>LED</value>
      <footprint>LED_SMD:LED_0805_2012Metric_Pad1.15x1.40mm_HandSolder</footprint>
      <datasheet>https://www.mouser.com/ProductDetail/ROHM-Semiconductor/SML-H12V8TT86?qs=493kPxzlxfI59R5PYPQRxg%3D%3D</datasheet>
      <libsource lib="Device" part="LED" description="Light emitting diode"/>
      <property name="Sheetname" value=""/>
      <property name="Sheetfile" value="basic_microcontroller.kicad_sch"/>
      <property name="ki_description" value="Light emitting diode"/>
      <property name="ki_keywords" value="LED diode"/>
      <sheetpath names="/" tstamps="/"/>
      <tstamps>0de26372-bb64-4c09-88b0-9a112b711065</tstamps>
    </comp>
    <comp ref="F1">
      <value>Polyfuse</value>
      <footprint>Fuse:Fuse_1206_3216Metric_Pad1.42x1.75mm_HandSolder</footprint>
      <datasheet>https://www.mouser.com/ProductDetail/Bourns/MF-NSHT020KX-2?qs=XeJtXLiO41RZL4g88duWeg%3D%3D</datasheet>
      <libsource lib="Device" part="Polyfuse" description="Resettable fuse, polymeric positive temperature coefficient"/>
      <property name="Sheetname" value=""/>
      <property name="Sheetfile" value="basic_microcontroller.kicad_sch"/>
      <property name="ki_description" value="Resettable fuse, polymeric positive temperature coefficient"/>
      <property name="ki_keywords" value="resettable fuse PTC PPTC polyfuse polyswitch"/>
      <sheetpath names="/" tstamps="/"/>
      <tstamps>6fcd7267-3121-4816-9b4e-21e1ef3d1962</tstamps>
    </comp>
    <comp ref="J1">
      <value>USB_C_Receptacle_USB2.0</value>
      <footprint>basic_microcontroller:USB480003A</footprint>
      <datasheet>https://www.mouser.com/ProductDetail/GCT/USB4800-03-A?qs=vvQtp7zwQdMkfG8vViEZoQ%3D%3D</datasheet>
      <libsource lib="Connector" part="USB_C_Receptacle_USB2.0" description="USB 2.0-only Type-C Receptacle connector"/>
      <property name="Sheetname" value=""/>
      <property name="Sheetfile" value="basic_microcontroller.kicad_sch"/>
      <property name="ki_description" value="USB 2.0-only Type-C Receptacle connector"/>
      <property name="ki_keywords" value="usb universal serial bus type-C USB2.0"/>
      <sheetpath names="/" tstamps="/"/>
      <tstamps>d0c63f25-55c8-4272-a79d-49c4496836b4</tstamps>
    </comp>
    <comp ref="J2">
      <value>AVR-ISP-6</value>
      <footprint>Connector_IDC:IDC-Header_2x03_P2.54mm_Vertical</footprint>
      <datasheet>https://www.mouser.com/ProductDetail/TE-Connectivity/1761681-1?qs=BqFpTYCQ3dLAeZ2wzdz7aw%3D%3D</datasheet>
      <libsource lib="Connector" part="AVR-ISP-6" description="Atmel 6-pin ISP connector"/>
      <property name="Sheetname" value=""/>
      <property name="Sheetfile" value="basic_microcontroller.kicad_sch"/>
      <property name="ki_description" value="Atmel 6-pin ISP connector"/>
      <property name="ki_keywords" value="AVR ISP Connector"/>
      <sheetpath names="/" tstamps="/"/>
      <tstamps>6badb0fd-bf35-4700-98b2-2c42e0dde7b8</tstamps>
    </comp>
    <comp ref="J3">
      <value>Screw_Terminal_01x02</value>
      <footprint>TerminalBlock_Phoenix:TerminalBlock_Phoenix_MPT-0,5-2-2.54_1x02_P2.54mm_Horizontal</footprint>
      <datasheet>https://www.mouser.com/ProductDetail/Amphenol-Anytek/VN02A1500000G?qs=Mv7BduZupUgf8d3Xo6xdxw%3D%3D</datasheet>
      <libsource lib="Connector" part="Screw_Terminal_01x02" description="Generic screw terminal, single row, 01x02, script generated (kicad-library-utils/schlib/autogen/connector/)"/>
      <property name="Sheetname" value=""/>
      <property name="Sheetfile" value="basic_microcontroller.kicad_sch"/>
      <property name="ki_description" value="Generic screw terminal, single row, 01x02, script generated (kicad-library-utils/schlib/autogen/connector/)"/>
      <property name="ki_keywords" value="screw terminal"/>
      <sheetpath names="/" tstamps="/"/>
      <tstamps>a5fb8023-053a-4954-b8d7-f1d333fec2f5</tstamps>
    </comp>
    <comp ref="R1">
      <value>22</value>
      <footprint>Resistor_SMD:R_0805_2012Metric_Pad1.20x1.40mm_HandSolder</footprint>
      <datasheet>https://www.mouser.com/ProductDetail/667-ERJ-6ENF22R0V</datasheet>
      <libsource lib="Device" part="R_US" description="Resistor, US symbol"/>
      <property name="Sheetname" value=""/>
      <property name="Sheetfile" value="basic_microcontroller.kicad_sch"/>
      <property name="ki_description" value="Resistor, US symbol"/>
      <property name="ki_keywords" value="R res resistor"/>
      <sheetpath names="/" tstamps="/"/>
      <tstamps>dc50f44e-df25-4116-b738-e71d9e7c0963</tstamps>
    </comp>
    <comp ref="R2">
      <value>22</value>
      <footprint>Resistor_SMD:R_0805_2012Metric_Pad1.20x1.40mm_HandSolder</footprint>
      <datasheet>https://www.mouser.com/ProductDetail/667-ERJ-6ENF22R0V</datasheet>
      <libsource lib="Device" part="R_US" description="Resistor, US symbol"/>
      <property name="Sheetname" value=""/>
      <property name="Sheetfile" value="basic_microcontroller.kicad_sch"/>
      <property name="ki_description" value="Resistor, US symbol"/>
      <property name="ki_keywords" value="R res resistor"/>
      <sheetpath names="/" tstamps="/"/>
      <tstamps>0ff45c54-e857-4a90-bbe9-d2a27c3d8a46</tstamps>
    </comp>
    <comp ref="R3">
      <value>5.1k</value>
      <footprint>Resistor_SMD:R_0603_1608Metric_Pad0.98x0.95mm_HandSolder</footprint>
      <libsource lib="Device" part="R_US" description="Resistor, US symbol"/>
      <property name="Sheetname" value=""/>
      <property name="Sheetfile" value="basic_microcontroller.kicad_sch"/>
      <property name="ki_description" value="Resistor, US symbol"/>
      <property name="ki_keywords" value="R res resistor"/>
      <sheetpath names="/" tstamps="/"/>
      <tstamps>2dbf0e46-8c7a-413c-b20c-a8d6af446b33</tstamps>
    </comp>
    <comp ref="R4">
      <value>1M</value>
      <footprint>Resistor_SMD:R_0805_2012Metric_Pad1.20x1.40mm_HandSolder</footprint>
      <datasheet>https://www.mouser.com/ProductDetail/660-HV732ARTTD105J</datasheet>
      <libsource lib="Device" part="R_US" description="Resistor, US symbol"/>
      <property name="Sheetname" value=""/>
      <property name="Sheetfile" value="basic_microcontroller.kicad_sch"/>
      <property name="ki_description" value="Resistor, US symbol"/>
      <property name="ki_keywords" value="R res resistor"/>
      <sheetpath names="/" tstamps="/"/>
      <tstamps>447a422c-1ddc-4104-8d4c-b306f48c192f</tstamps>
    </comp>
    <comp ref="R5">
      <value>5.1k</value>
      <footprint>Resistor_SMD:R_0603_1608Metric_Pad0.98x0.95mm_HandSolder</footprint>
      <libsource lib="Device" part="R_US" description="Resistor, US symbol"/>
      <property name="Sheetname" value=""/>
      <property name="Sheetfile" value="basic_microcontroller.kicad_sch"/>
      <property name="ki_description" value="Resistor, US symbol"/>
      <property name="ki_keywords" value="R res resistor"/>
      <sheetpath names="/" tstamps="/"/>
      <tstamps>83297adb-cac8-485f-b20c-1dae3c5d844e</tstamps>
    </comp>
    <comp ref="R6">
      <value>5.1k</value>
      <footprint>Resistor_SMD:R_0603_1608Metric_Pad0.98x0.95mm_HandSolder</footprint>
      <libsource lib="Device" part="R_US" description="Resistor, US symbol"/>
      <property name="Sheetname" value=""/>
      <property name="Sheetfile" value="basic_microcontroller.kicad_sch"/>
      <property name="ki_description" value="Resistor, US symbol"/>
      <property name="ki_keywords" value="R res resistor"/>
      <sheetpath names="/" tstamps="/"/>
      <tstamps>6c067782-73fe-4c67-acd7-ffed2bc5801c</tstamps>
    </comp>
    <comp ref="R7">
      <value>140</value>
      <footprint>Resistor_SMD:R_0805_2012Metric_Pad1.20x1.40mm_HandSolder</footprint>
      <datasheet>https://www.mouser.com/ProductDetail/652-CR0805FX-1400ELF</datasheet>
      <libsource lib="Device" part="R_US" description="Resistor, US symbol"/>
      <property name="Sheetname" value=""/>
      <property name="Sheetfile" value="basic_microcontroller.kicad_sch"/>
      <property name="ki_description" value="Resistor, US symbol"/>
      <property name="ki_keywords" value="R res resistor"/>
      <sheetpath names="/" tstamps="/"/>
      <tstamps>e319bd0e-98dd-42da-aed5-6db24f4076ef</tstamps>
    </comp>
    <comp ref="R8">
      <value>140</value>
      <footprint>Resistor_SMD:R_0805_2012Metric_Pad1.20x1.40mm_HandSolder</footprint>
      <datasheet>https://www.mouser.com/ProductDetail/652-CR0805FX-1400ELF</datasheet>
      <libsource lib="Device" part="R_US" description="Resistor, US symbol"/>
      <property name="Sheetname" value=""/>
      <property name="Sheetfile" value="basic_microcontroller.kicad_sch"/>
      <property name="ki_description" value="Resistor, US symbol"/>
      <property name="ki_keywords" value="R res resistor"/>
      <sheetpath names="/" tstamps="/"/>
      <tstamps>1cf92108-9449-4251-9bea-83bfcc311c6a</tstamps>
    </comp>
    <comp ref="R9">
      <value>140</value>
      <footprint>Resistor_SMD:R_0805_2012Metric_Pad1.20x1.40mm_HandSolder</footprint>
      <datasheet>https://www.mouser.com/ProductDetail/652-CR0805FX-1400ELF</datasheet>
      <libsource lib="Device" part="R_US" description="Resistor, US symbol"/>
      <property name="Sheetname" value=""/>
      <property name="Sheetfile" value="basic_microcontroller.kicad_sch"/>
      <property name="ki_description" value="Resistor, US symbol"/>
      <property name="ki_keywords" value="R res resistor"/>
      <sheetpath names="/" tstamps="/"/>
      <tstamps>392a51e9-9138-4016-9d97-fc19e70940fd</tstamps>
    </comp>
    <comp ref="R10">
      <value>140</value>
      <footprint>Resistor_SMD:R_0805_2012Metric_Pad1.20x1.40mm_HandSolder</footprint>
      <datasheet>https://www.mouser.com/ProductDetail/652-CR0805FX-1400ELF</datasheet>
      <libsource lib="Device" part="R_US" description="Resistor, US symbol"/>
      <property name="Sheetname" value=""/>
      <property name="Sheetfile" value="basic_microcontroller.kicad_sch"/>
      <property name="ki_description" value="Resistor, US symbol"/>
      <property name="ki_keywords" value="R res resistor"/>
      <sheetpath names="/" tstamps="/"/>
      <tstamps>ca49edbb-cbcb-4a44-ad72-6560f5711b30</tstamps>
    </comp>
    <comp ref="R11">
      <value>140</value>
      <footprint>Resistor_SMD:R_0805_2012Metric_Pad1.20x1.40mm_HandSolder</footprint>
      <datasheet>https://www.mouser.com/ProductDetail/652-CR0805FX-1400ELF</datasheet>
      <libsource lib="Device" part="R_US" description="Resistor, US symbol"/>
      <property name="Sheetname" value=""/>
      <property name="Sheetfile" value="basic_microcontroller.kicad_sch"/>
      <property name="ki_description" value="Resistor, US symbol"/>
      <property name="ki_keywords" value="R res resistor"/>
      <sheetpath names="/" tstamps="/"/>
      <tstamps>2452882d-d8f4-4cf4-ab88-0640c04d442e</tstamps>
    </comp>
    <comp ref="R12">
      <value>140</value>
      <footprint>Resistor_SMD:R_0805_2012Metric_Pad1.20x1.40mm_HandSolder</footprint>
      <datasheet>https://www.mouser.com/ProductDetail/652-CR0805FX-1400ELF</datasheet>
      <libsource lib="Device" part="R_US" description="Resistor, US symbol"/>
      <property name="Sheetname" value=""/>
      <property name="Sheetfile" value="basic_microcontroller.kicad_sch"/>
      <property name="ki_description" value="Resistor, US symbol"/>
      <property name="ki_keywords" value="R res resistor"/>
      <sheetpath names="/" tstamps="/"/>
      <tstamps>cbb794ee-4bae-478e-ad1c-8a6f2cdd1e31</tstamps>
    </comp>
    <comp ref="R13">
      <value>140</value>
      <footprint>Resistor_SMD:R_0805_2012Metric_Pad1.20x1.40mm_HandSolder</footprint>
      <datasheet>https://www.mouser.com/ProductDetail/652-CR0805FX-1400ELF</datasheet>
      <libsource lib="Device" part="R_US" description="Resistor, US symbol"/>
      <property name="Sheetname" value=""/>
      <property name="Sheetfile" value="basic_microcontroller.kicad_sch"/>
      <property name="ki_description" value="Resistor, US symbol"/>
      <property name="ki_keywords" value="R res resistor"/>
      <sheetpath names="/" tstamps="/"/>
      <tstamps>eec65513-d414-4083-bbaa-726973c4bf25</tstamps>
    </comp>
    <comp ref="R14">
      <value>140</value>
      <footprint>Resistor_SMD:R_0805_2012Metric_Pad1.20x1.40mm_HandSolder</footprint>
      <datasheet>https://www.mouser.com/ProductDetail/652-CR0805FX-1400ELF</datasheet>
      <libsource lib="Device" part="R_US" description="Resistor, US symbol"/>
      <property name="Sheetname" value=""/>
      <property name="Sheetfile" value="basic_microcontroller.kicad_sch"/>
      <property name="ki_description" value="Resistor, US symbol"/>
      <property name="ki_keywords" value="R res resistor"/>
      <sheetpath names="/" tstamps="/"/>
      <tstamps>4cc414a4-c940-43b1-b4bc-505435cee53e</tstamps>
    </comp>
    <comp ref="R15">
      <value>140</value>
      <footprint>Resistor_SMD:R_0805_2012Metric_Pad1.20x1.40mm_HandSolder</footprint>
      <datasheet>https://www.mouser.com/ProductDetail/652-CR0805FX-1400ELF</datasheet>
      <libsource lib="Device" part="R_US" description="Resistor, US symbol"/>
      <property name="Sheetname" value=""/>
      <property name="Sheetfile" value="basic_microcontroller.kicad_sch"/>
      <property name="ki_description" value="Resistor, US symbol"/>
      <property name="ki_keywords" value="R res resistor"/>
      <sheetpath names="/" tstamps="/"/>
      <tstamps>fa897619-0075-4aa9-b04a-8dd16c715f2e</tstamps>
    </comp>
    <comp ref="R16">
      <value>140</value>
      <footprint>Resistor_SMD:R_0805_2012Metric_Pad1.20x1.40mm_HandSolder</footprint>
      <datasheet>https://www.mouser.com/ProductDetail/652-CR0805FX-1400ELF</datasheet>
      <libsource lib="Device" part="R_US" description="Resistor, US symbol"/>
      <property name="Sheetname" value=""/>
      <property name="Sheetfile" value="basic_microcontroller.kicad_sch"/>
      <property name="ki_description" value="Resistor, US symbol"/>
      <property name="ki_keywords" value="R res resistor"/>
      <sheetpath names="/" tstamps="/"/>
      <tstamps>ee50573f-63cc-4db2-904e-6d55b1f3c9d3</tstamps>
    </comp>
    <comp ref="R17">
      <value>140</value>
      <footprint>Resistor_SMD:R_0805_2012Metric_Pad1.20x1.40mm_HandSolder</footprint>
      <datasheet>https://www.mouser.com/ProductDetail/652-CR0805FX-1400ELF</datasheet>
      <libsource lib="Device" part="R_US" description="Resistor, US symbol"/>
      <property name="Sheetname" value=""/>
      <property name="Sheetfile" value="basic_microcontroller.kicad_sch"/>
      <property name="ki_description" value="Resistor, US symbol"/>
      <property name="ki_keywords" value="R res resistor"/>
      <sheetpath names="/" tstamps="/"/>
      <tstamps>f680f07a-bb46-48ad-86f8-3ef2be777c09</tstamps>
    </comp>
    <comp ref="R18">
      <value>140</value>
      <footprint>Resistor_SMD:R_0805_2012Metric_Pad1.20x1.40mm_HandSolder</footprint>
      <datasheet>https://www.mouser.com/ProductDetail/652-CR0805FX-1400ELF</datasheet>
      <libsource lib="Device" part="R_US" description="Resistor, US symbol"/>
      <property name="Sheetname" value=""/>
      <property name="Sheetfile" value="basic_microcontroller.kicad_sch"/>
      <property name="ki_description" value="Resistor, US symbol"/>
      <property name="ki_keywords" value="R res resistor"/>
      <sheetpath names="/" tstamps="/"/>
      <tstamps>ddb5db29-d934-4c93-b440-8a42033663a1</tstamps>
    </comp>
    <comp ref="R19">
      <value>140</value>
      <footprint>Resistor_SMD:R_0805_2012Metric_Pad1.20x1.40mm_HandSolder</footprint>
      <datasheet>https://www.mouser.com/ProductDetail/652-CR0805FX-1400ELF</datasheet>
      <libsource lib="Device" part="R_US" description="Resistor, US symbol"/>
      <property name="Sheetname" value=""/>
      <property name="Sheetfile" value="basic_microcontroller.kicad_sch"/>
      <property name="ki_description" value="Resistor, US symbol"/>
      <property name="ki_keywords" value="R res resistor"/>
      <sheetpath names="/" tstamps="/"/>
      <tstamps>5a762427-c104-491c-a1b4-b6ab40e26eae</tstamps>
    </comp>
    <comp ref="R20">
      <value>140</value>
      <footprint>Resistor_SMD:R_0805_2012Metric_Pad1.20x1.40mm_HandSolder</footprint>
      <datasheet>https://www.mouser.com/ProductDetail/652-CR0805FX-1400ELF</datasheet>
      <libsource lib="Device" part="R_US" description="Resistor, US symbol"/>
      <property name="Sheetname" value=""/>
      <property name="Sheetfile" value="basic_microcontroller.kicad_sch"/>
      <property name="ki_description" value="Resistor, US symbol"/>
      <property name="ki_keywords" value="R res resistor"/>
      <sheetpath names="/" tstamps="/"/>
      <tstamps>df21dd8b-c2b2-45b5-a564-f5cf6d38c721</tstamps>
    </comp>
    <comp ref="R21">
      <value>140</value>
      <footprint>Resistor_SMD:R_0805_2012Metric_Pad1.20x1.40mm_HandSolder</footprint>
      <datasheet>https://www.mouser.com/ProductDetail/652-CR0805FX-1400ELF</datasheet>
      <libsource lib="Device" part="R_US" description="Resistor, US symbol"/>
      <property name="Sheetname" value=""/>
      <property name="Sheetfile" value="basic_microcontroller.kicad_sch"/>
      <property name="ki_description" value="Resistor, US symbol"/>
      <property name="ki_keywords" value="R res resistor"/>
      <sheetpath names="/" tstamps="/"/>
      <tstamps>93b87b6f-c991-4e76-a3d1-9d8f46b246fb</tstamps>
    </comp>
    <comp ref="R22">
      <value>140</value>
      <footprint>Resistor_SMD:R_0805_2012Metric_Pad1.20x1.40mm_HandSolder</footprint>
      <datasheet>https://www.mouser.com/ProductDetail/652-CR0805FX-1400ELF</datasheet>
      <libsource lib="Device" part="R_US" description="Resistor, US symbol"/>
      <property name="Sheetname" value=""/>
      <property name="Sheetfile" value="basic_microcontroller.kicad_sch"/>
      <property name="ki_description" value="Resistor, US symbol"/>
      <property name="ki_keywords" value="R res resistor"/>
      <sheetpath names="/" tstamps="/"/>
      <tstamps>c68212a8-7611-460d-b923-1cef6546fa86</tstamps>
    </comp>
    <comp ref="R23">
      <value>140</value>
      <footprint>Resistor_SMD:R_0805_2012Metric_Pad1.20x1.40mm_HandSolder</footprint>
      <datasheet>https://www.mouser.com/ProductDetail/652-CR0805FX-1400ELF</datasheet>
      <libsource lib="Device" part="R_US" description="Resistor, US symbol"/>
      <property name="Sheetname" value=""/>
      <property name="Sheetfile" value="basic_microcontroller.kicad_sch"/>
      <property name="ki_description" value="Resistor, US symbol"/>
      <property name="ki_keywords" value="R res resistor"/>
      <sheetpath names="/" tstamps="/"/>
      <tstamps>8fe24795-7413-4a94-9106-214c8ce60e13</tstamps>
    </comp>
    <comp ref="R24">
      <value>140</value>
      <footprint>Resistor_SMD:R_0805_2012Metric_Pad1.20x1.40mm_HandSolder</footprint>
      <datasheet>https://www.mouser.com/ProductDetail/652-CR0805FX-1400ELF</datasheet>
      <libsource lib="Device" part="R_US" description="Resistor, US symbol"/>
      <property name="Sheetname" value=""/>
      <property name="Sheetfile" value="basic_microcontroller.kicad_sch"/>
      <property name="ki_description" value="Resistor, US symbol"/>
      <property name="ki_keywords" value="R res resistor"/>
      <sheetpath names="/" tstamps="/"/>
      <tstamps>70727f3e-1554-43c1-8931-bf7a2f00b9c7</tstamps>
    </comp>
    <comp ref="R25">
      <value>140</value>
      <footprint>Resistor_SMD:R_0805_2012Metric_Pad1.20x1.40mm_HandSolder</footprint>
      <datasheet>https://www.mouser.com/ProductDetail/652-CR0805FX-1400ELF</datasheet>
      <libsource lib="Device" part="R_US" description="Resistor, US symbol"/>
      <property name="Sheetname" value=""/>
      <property name="Sheetfile" value="basic_microcontroller.kicad_sch"/>
      <property name="ki_description" value="Resistor, US symbol"/>
      <property name="ki_keywords" value="R res resistor"/>
      <sheetpath names="/" tstamps="/"/>
      <tstamps>e6ec7114-d3a7-47e8-80e0-883abc682bbf</tstamps>
    </comp>
    <comp ref="R26">
      <value>140</value>
      <footprint>Resistor_SMD:R_0805_2012Metric_Pad1.20x1.40mm_HandSolder</footprint>
      <datasheet>https://www.mouser.com/ProductDetail/652-CR0805FX-1400ELF</datasheet>
      <libsource lib="Device" part="R_US" description="Resistor, US symbol"/>
      <property name="Sheetname" value=""/>
      <property name="Sheetfile" value="basic_microcontroller.kicad_sch"/>
      <property name="ki_description" value="Resistor, US symbol"/>
      <property name="ki_keywords" value="R res resistor"/>
      <sheetpath names="/" tstamps="/"/>
      <tstamps>ff660d40-030a-4c2b-9996-f02e73098169</tstamps>
    </comp>
    <comp ref="R27">
      <value>140</value>
      <footprint>Resistor_SMD:R_0805_2012Metric_Pad1.20x1.40mm_HandSolder</footprint>
      <datasheet>https://www.mouser.com/ProductDetail/652-CR0805FX-1400ELF</datasheet>
      <libsource lib="Device" part="R_US" description="Resistor, US symbol"/>
      <property name="Sheetname" value=""/>
      <property name="Sheetfile" value="basic_microcontroller.kicad_sch"/>
      <property name="ki_description" value="Resistor, US symbol"/>
      <property name="ki_keywords" value="R res resistor"/>
      <sheetpath names="/" tstamps="/"/>
      <tstamps>bc751c9e-8e74-4ea6-830a-029a3bf34a75</tstamps>
    </comp>
    <comp ref="R28">
      <value>140</value>
      <footprint>Resistor_SMD:R_0805_2012Metric_Pad1.20x1.40mm_HandSolder</footprint>
      <datasheet>https://www.mouser.com/ProductDetail/652-CR0805FX-1400ELF</datasheet>
      <libsource lib="Device" part="R_US" description="Resistor, US symbol"/>
      <property name="Sheetname" value=""/>
      <property name="Sheetfile" value="basic_microcontroller.kicad_sch"/>
      <property name="ki_description" value="Resistor, US symbol"/>
      <property name="ki_keywords" value="R res resistor"/>
      <sheetpath names="/" tstamps="/"/>
      <tstamps>ab3c1cb3-6076-4e61-bf2e-55409b982d80</tstamps>
    </comp>
    <comp ref="R29">
      <value>140</value>
      <footprint>Resistor_SMD:R_0805_2012Metric_Pad1.20x1.40mm_HandSolder</footprint>
      <datasheet>https://www.mouser.com/ProductDetail/652-CR0805FX-1400ELF</datasheet>
      <libsource lib="Device" part="R_US" description="Resistor, US symbol"/>
      <property name="Sheetname" value=""/>
      <property name="Sheetfile" value="basic_microcontroller.kicad_sch"/>
      <property name="ki_description" value="Resistor, US symbol"/>
      <property name="ki_keywords" value="R res resistor"/>
      <sheetpath names="/" tstamps="/"/>
      <tstamps>d10a715c-b44a-4c66-bd7b-51e08e8a6cae</tstamps>
    </comp>
    <comp ref="R30">
      <value>140</value>
      <footprint>Resistor_SMD:R_0805_2012Metric_Pad1.20x1.40mm_HandSolder</footprint>
      <datasheet>https://www.mouser.com/ProductDetail/652-CR0805FX-1400ELF</datasheet>
      <libsource lib="Device" part="R_US" description="Resistor, US symbol"/>
      <property name="Sheetname" value=""/>
      <property name="Sheetfile" value="basic_microcontroller.kicad_sch"/>
      <property name="ki_description" value="Resistor, US symbol"/>
      <property name="ki_keywords" value="R res resistor"/>
      <sheetpath names="/" tstamps="/"/>
      <tstamps>14142463-7514-48de-8ed3-6187459c78ab</tstamps>
    </comp>
    <comp ref="R31">
      <value>140</value>
      <footprint>Resistor_SMD:R_0805_2012Metric_Pad1.20x1.40mm_HandSolder</footprint>
      <datasheet>https://www.mouser.com/ProductDetail/652-CR0805FX-1400ELF</datasheet>
      <libsource lib="Device" part="R_US" description="Resistor, US symbol"/>
      <property name="Sheetname" value=""/>
      <property name="Sheetfile" value="basic_microcontroller.kicad_sch"/>
      <property name="ki_description" value="Resistor, US symbol"/>
      <property name="ki_keywords" value="R res resistor"/>
      <sheetpath names="/" tstamps="/"/>
      <tstamps>2fbf84ef-6008-4d52-a5b1-5858f369d2a3</tstamps>
    </comp>
    <comp ref="R32">
      <value>140</value>
      <footprint>Resistor_SMD:R_0805_2012Metric_Pad1.20x1.40mm_HandSolder</footprint>
      <datasheet>https://www.mouser.com/ProductDetail/652-CR0805FX-1400ELF</datasheet>
      <libsource lib="Device" part="R_US" description="Resistor, US symbol"/>
      <property name="Sheetname" value=""/>
      <property name="Sheetfile" value="basic_microcontroller.kicad_sch"/>
      <property name="ki_description" value="Resistor, US symbol"/>
      <property name="ki_keywords" value="R res resistor"/>
      <sheetpath names="/" tstamps="/"/>
      <tstamps>13e3c6be-10f9-472e-ad16-26ec83496221</tstamps>
    </comp>
    <comp ref="R33">
      <value>140</value>
      <footprint>Resistor_SMD:R_0805_2012Metric_Pad1.20x1.40mm_HandSolder</footprint>
      <datasheet>https://www.mouser.com/ProductDetail/652-CR0805FX-1400ELF</datasheet>
      <libsource lib="Device" part="R_US" description="Resistor, US symbol"/>
      <property name="Sheetname" value=""/>
      <property name="Sheetfile" value="basic_microcontroller.kicad_sch"/>
      <property name="ki_description" value="Resistor, US symbol"/>
      <property name="ki_keywords" value="R res resistor"/>
      <sheetpath names="/" tstamps="/"/>
      <tstamps>223fd29d-95d7-4caf-965b-1e9709165c73</tstamps>
    </comp>
    <comp ref="R34">
      <value>91</value>
      <footprint>Resistor_SMD:R_0805_2012Metric_Pad1.20x1.40mm_HandSolder</footprint>
      <datasheet>https://www.mouser.com/ProductDetail/71-CRCW080591R0FKEAC</datasheet>
      <libsource lib="Device" part="R_US" description="Resistor, US symbol"/>
      <property name="Sheetname" value=""/>
      <property name="Sheetfile" value="basic_microcontroller.kicad_sch"/>
      <property name="ki_description" value="Resistor, US symbol"/>
      <property name="ki_keywords" value="R res resistor"/>
      <sheetpath names="/" tstamps="/"/>
      <tstamps>042f89f3-6bcd-4140-b7b3-4c0f620071f0</tstamps>
    </comp>
    <comp ref="R35">
      <value>91</value>
      <footprint>Resistor_SMD:R_0805_2012Metric_Pad1.20x1.40mm_HandSolder</footprint>
      <datasheet>https://www.mouser.com/ProductDetail/71-CRCW080591R0FKEAC</datasheet>
      <libsource lib="Device" part="R_US" description="Resistor, US symbol"/>
      <property name="Sheetname" value=""/>
      <property name="Sheetfile" value="basic_microcontroller.kicad_sch"/>
      <property name="ki_description" value="Resistor, US symbol"/>
      <property name="ki_keywords" value="R res resistor"/>
      <sheetpath names="/" tstamps="/"/>
      <tstamps>76d0c911-dbac-4008-a059-7999582b9bf0</tstamps>
    </comp>
    <comp ref="R36">
      <value>10k</value>
      <footprint>Resistor_SMD:R_0805_2012Metric_Pad1.20x1.40mm_HandSolder</footprint>
      <datasheet>https://www.mouser.com/ProductDetail/Bourns/CMP0805-FX-1002ELF?qs=sGAEpiMZZMtlubZbdhIBIIPWN1VQSu3w%252BKNanILcNso%3D</datasheet>
      <libsource lib="Device" part="R_Small_US" description="Resistor, small US symbol"/>
      <property name="Sheetname" value=""/>
      <property name="Sheetfile" value="basic_microcontroller.kicad_sch"/>
      <property name="ki_description" value="Resistor, small US symbol"/>
      <property name="ki_keywords" value="r resistor"/>
      <sheetpath names="/" tstamps="/"/>
      <tstamps>d9b9749d-b780-45ec-b618-5aca679aafaf</tstamps>
    </comp>
    <comp ref="R37">
      <value>10k</value>
      <footprint>Resistor_SMD:R_0805_2012Metric_Pad1.20x1.40mm_HandSolder</footprint>
      <datasheet>https://www.mouser.com/ProductDetail/Bourns/CMP0805-FX-1002ELF?qs=sGAEpiMZZMtlubZbdhIBIIPWN1VQSu3w%252BKNanILcNso%3D</datasheet>
      <libsource lib="Device" part="R_Small_US" description="Resistor, small US symbol"/>
      <property name="Sheetname" value=""/>
      <property name="Sheetfile" value="basic_microcontroller.kicad_sch"/>
      <property name="ki_description" value="Resistor, small US symbol"/>
      <property name="ki_keywords" value="r resistor"/>
      <sheetpath names="/" tstamps="/"/>
      <tstamps>93c419d0-87a3-4ed8-a911-ac5411e4f55c</tstamps>
    </comp>
    <comp ref="R38">
      <value>140</value>
      <footprint>Resistor_SMD:R_0805_2012Metric_Pad1.20x1.40mm_HandSolder</footprint>
      <datasheet>https://www.mouser.com/ProductDetail/652-CR0805FX-1400ELF</datasheet>
      <libsource lib="Device" part="R_Small_US" description="Resistor, small US symbol"/>
      <property name="Sheetname" value=""/>
      <property name="Sheetfile" value="basic_microcontroller.kicad_sch"/>
      <property name="ki_description" value="Resistor, small US symbol"/>
      <property name="ki_keywords" value="r resistor"/>
      <sheetpath names="/" tstamps="/"/>
      <tstamps>0d2fdf6f-9b5b-45bd-8131-7581b1fbaca2</tstamps>
    </comp>
    <comp ref="S1">
      <value>Pushbutton Switch</value>
      <footprint>basic_microcontroller:Pushbutton Switch</footprint>
      <datasheet>https://www.mouser.com/ProductDetail/688-SPEJ110100</datasheet>
      <fields>
        <field name="Height">8</field>
        <field name="Manufacturer_Name">ALPS Electric</field>
        <field name="Manufacturer_Part_Number">SPEJ110100</field>
        <field name="Mouser Part Number">688-SPEJ110100</field>
        <field name="Mouser Price/Stock">https://www.mouser.co.uk/ProductDetail/Alps-Alpine/SPEJ110100?qs=YMSFtX0bdJBg5hL%2FI29c%252BQ%3D%3D</field>
      </fields>
      <libsource lib="basic_microcontroller" part="SPEJ110100" description="DPDT Momentary Push Button Switch, PCB, 14V dc"/>
      <property name="Height" value="8"/>
      <property name="Mouser Part Number" value="688-SPEJ110100"/>
      <property name="Mouser Price/Stock" value="https://www.mouser.co.uk/ProductDetail/Alps-Alpine/SPEJ110100?qs=YMSFtX0bdJBg5hL%2FI29c%252BQ%3D%3D"/>
      <property name="Manufacturer_Name" value="ALPS Electric"/>
      <property name="Manufacturer_Part_Number" value="SPEJ110100"/>
      <property name="Sheetname" value=""/>
      <property name="Sheetfile" value="basic_microcontroller.kicad_sch"/>
      <property name="ki_description" value="DPDT Momentary Push Button Switch, PCB, 14V dc"/>
      <sheetpath names="/" tstamps="/"/>
      <tstamps>1be4e713-3c50-4a30-a0d5-f314d6167766</tstamps>
    </comp>
    <comp ref="U1">
      <value>ATmega32U4-A</value>
      <footprint>Package_QFP:TQFP-44_10x10mm_P0.8mm</footprint>
      <datasheet>http://ww1.microchip.com/downloads/en/DeviceDoc/Atmel-7766-8-bit-AVR-ATmega16U4-32U4_Datasheet.pdf</datasheet>
      <libsource lib="MCU_Microchip_ATmega" part="ATmega32U4-A" description="16MHz, 32kB Flash, 2.5kB SRAM, 1kB EEPROM, USB 2.0, TQFP-44"/>
      <property name="Sheetname" value=""/>
      <property name="Sheetfile" value="basic_microcontroller.kicad_sch"/>
      <property name="ki_description" value="16MHz, 32kB Flash, 2.5kB SRAM, 1kB EEPROM, USB 2.0, TQFP-44"/>
      <property name="ki_keywords" value="AVR 8bit Microcontroller MegaAVR USB"/>
      <sheetpath names="/" tstamps="/"/>
      <tstamps>3c7a3d6f-4c3a-4841-8830-f5e4cede9179</tstamps>
    </comp>
    <comp ref="Y1">
      <value>8MHz</value>
      <footprint>basic_microcontroller:ECS80185PXGMTR</footprint>
      <datasheet>https://www.mouser.com/ProductDetail/ECS/ECS-80-18-5PX-GM-TR?qs=amGC7iS6iy9i4EiBY7c3iQ%3D%3D</datasheet>
      <libsource lib="Device" part="Crystal" description="Two pin crystal"/>
      <property name="Sheetname" value=""/>
      <property name="Sheetfile" value="basic_microcontroller.kicad_sch"/>
      <property name="ki_description" value="Two pin crystal"/>
      <property name="ki_keywords" value="quartz ceramic resonator oscillator"/>
      <sheetpath names="/" tstamps="/"/>
      <tstamps>b6f20877-f44e-48a9-8b3c-f9ddefba2b06</tstamps>
    </comp>
  </components>
  <libparts>
    <libpart lib="Connector" part="AVR-ISP-6">
      <description>Atmel 6-pin ISP connector</description>
      <docs> ~</docs>
      <footprints>
        <fp>IDC?Header*2x03*</fp>
        <fp>Pin?Header*2x03*</fp>
      </footprints>
      <fields>
        <field name="Reference">J</field>
        <field name="Value">AVR-ISP-6</field>
        <field name="Datasheet"> ~</field>
      </fields>
      <pins>
        <pin num="1" name="MISO" type="passive"/>
        <pin num="2" name="VCC" type="passive"/>
        <pin num="3" name="SCK" type="passive"/>
        <pin num="4" name="MOSI" type="passive"/>
        <pin num="5" name="~{RST}" type="passive"/>
        <pin num="6" name="GND" type="passive"/>
      </pins>
    </libpart>
    <libpart lib="Connector" part="Screw_Terminal_01x02">
      <description>Generic screw terminal, single row, 01x02, script generated (kicad-library-utils/schlib/autogen/connector/)</description>
      <docs>~</docs>
      <footprints>
        <fp>TerminalBlock*:*</fp>
      </footprints>
      <fields>
        <field name="Reference">J</field>
        <field name="Value">Screw_Terminal_01x02</field>
        <field name="Datasheet">~</field>
      </fields>
      <pins>
        <pin num="1" name="Pin_1" type="passive"/>
        <pin num="2" name="Pin_2" type="passive"/>
      </pins>
    </libpart>
    <libpart lib="Connector" part="USB_C_Receptacle_USB2.0">
      <description>USB 2.0-only Type-C Receptacle connector</description>
      <docs>https://www.mouser.com/ProductDetail/GCT/USB4800-03-A?qs=vvQtp7zwQdMkfG8vViEZoQ%3D%3D</docs>
      <footprints>
        <fp>USB*C*Receptacle*</fp>
      </footprints>
      <fields>
        <field name="Reference">J1</field>
        <field name="Value">USB_C_Receptacle_USB2.0</field>
        <field name="Footprint">basic_microcontroller:USB480003A</field>
        <field name="Datasheet">https://www.mouser.com/ProductDetail/GCT/USB4800-03-A?qs=vvQtp7zwQdMkfG8vViEZoQ%3D%3D</field>
      </fields>
      <pins>
        <pin num="A1" name="GND" type="passive"/>
        <pin num="A4" name="VBUS" type="passive"/>
        <pin num="A5" name="CC1" type="bidirectional"/>
        <pin num="A6" name="D+" type="bidirectional"/>
        <pin num="A7" name="D-" type="bidirectional"/>
        <pin num="A8" name="SBU1" type="bidirectional"/>
        <pin num="A9" name="VBUS" type="passive"/>
        <pin num="A12" name="GND" type="passive"/>
        <pin num="B1" name="GND" type="passive"/>
        <pin num="B4" name="VBUS" type="passive"/>
        <pin num="B5" name="CC2" type="bidirectional"/>
        <pin num="B6" name="D+" type="bidirectional"/>
        <pin num="B7" name="D-" type="bidirectional"/>
        <pin num="B8" name="SBU2" type="bidirectional"/>
        <pin num="B9" name="VBUS" type="passive"/>
        <pin num="B12" name="GND" type="passive"/>
        <pin num="MH" name="SHIELD" type="passive"/>
      </pins>
    </libpart>
    <libpart lib="Device" part="C">
      <description>Unpolarized capacitor</description>
      <docs>~</docs>
      <footprints>
        <fp>C_*</fp>
      </footprints>
      <fields>
        <field name="Reference">C</field>
        <field name="Value">C</field>
        <field name="Datasheet">~</field>
      </fields>
      <pins>
        <pin num="1" name="" type="passive"/>
        <pin num="2" name="" type="passive"/>
      </pins>
    </libpart>
    <libpart lib="Device" part="Crystal">
      <description>Two pin crystal</description>
      <docs>~</docs>
      <footprints>
        <fp>Crystal*</fp>
      </footprints>
      <fields>
        <field name="Reference">Y</field>
        <field name="Value">Crystal</field>
        <field name="Datasheet">~</field>
      </fields>
      <pins>
        <pin num="1" name="1" type="passive"/>
        <pin num="2" name="2" type="passive"/>
      </pins>
    </libpart>
    <libpart lib="Device" part="LED">
      <description>Light emitting diode</description>
      <docs>~</docs>
      <footprints>
        <fp>LED*</fp>
        <fp>LED_SMD:*</fp>
        <fp>LED_THT:*</fp>
      </footprints>
      <fields>
        <field name="Reference">D</field>
        <field name="Value">LED</field>
        <field name="Datasheet">~</field>
      </fields>
      <pins>
        <pin num="1" name="K" type="passive"/>
        <pin num="2" name="A" type="passive"/>
      </pins>
    </libpart>
    <libpart lib="Device" part="LED_ABRG">
      <description>RGB LED, anode/blue/red/green</description>
      <docs>~</docs>
      <footprints>
        <fp>LED*</fp>
        <fp>LED_SMD:*</fp>
        <fp>LED_THT:*</fp>
      </footprints>
      <fields>
        <field name="Reference">D</field>
        <field name="Value">LED_ABRG</field>
        <field name="Datasheet">~</field>
      </fields>
      <pins>
        <pin num="1" name="A" type="passive"/>
        <pin num="2" name="BK" type="passive"/>
        <pin num="3" name="RK" type="passive"/>
        <pin num="4" name="GK" type="passive"/>
      </pins>
    </libpart>
    <libpart lib="Device" part="Polyfuse">
      <description>Resettable fuse, polymeric positive temperature coefficient</description>
      <docs>~</docs>
      <footprints>
        <fp>*polyfuse*</fp>
        <fp>*PTC*</fp>
      </footprints>
      <fields>
        <field name="Reference">F</field>
        <field name="Value">Polyfuse</field>
        <field name="Datasheet">~</field>
      </fields>
      <pins>
        <pin num="1" name="" type="passive"/>
        <pin num="2" name="" type="passive"/>
      </pins>
    </libpart>
    <libpart lib="Device" part="R_Small_US">
      <description>Resistor, small US symbol</description>
      <docs>~</docs>
      <footprints>
        <fp>R_*</fp>
      </footprints>
      <fields>
        <field name="Reference">R</field>
        <field name="Value">R_Small_US</field>
        <field name="Datasheet">~</field>
      </fields>
      <pins>
        <pin num="1" name="" type="passive"/>
        <pin num="2" name="" type="passive"/>
      </pins>
    </libpart>
    <libpart lib="Device" part="R_US">
      <description>Resistor, US symbol</description>
      <docs>~</docs>
      <footprints>
        <fp>R_*</fp>
      </footprints>
      <fields>
        <field name="Reference">R</field>
        <field name="Value">R_US</field>
        <field name="Datasheet">~</field>
      </fields>
      <pins>
        <pin num="1" name="" type="passive"/>
        <pin num="2" name="" type="passive"/>
      </pins>
    </libpart>
    <libpart lib="MCU_Microchip_ATmega" part="ATmega32U4-A">
      <description>16MHz, 32kB Flash, 2.5kB SRAM, 1kB EEPROM, USB 2.0, TQFP-44</description>
      <docs>http://ww1.microchip.com/downloads/en/DeviceDoc/Atmel-7766-8-bit-AVR-ATmega16U4-32U4_Datasheet.pdf</docs>
      <footprints>
        <fp>TQFP*10x10mm*P0.8mm*</fp>
      </footprints>
      <fields>
        <field name="Reference">U1</field>
        <field name="Value">ATmega32U4-A</field>
        <field name="Footprint">Package_QFP:TQFP-44_10x10mm_P0.8mm</field>
        <field name="Datasheet">http://ww1.microchip.com/downloads/en/DeviceDoc/Atmel-7766-8-bit-AVR-ATmega16U4-32U4_Datasheet.pdf</field>
      </fields>
      <pins>
        <pin num="1" name="PE6" type="bidirectional"/>
        <pin num="2" name="UVCC" type="power_in"/>
        <pin num="3" name="D-" type="bidirectional"/>
        <pin num="4" name="D+" type="bidirectional"/>
        <pin num="5" name="UGND" type="passive"/>
        <pin num="6" name="UCAP" type="passive"/>
        <pin num="7" name="VBUS" type="input"/>
        <pin num="8" name="SS/PB0" type="bidirectional"/>
        <pin num="9" name="SCL/PB1" type="bidirectional"/>
        <pin num="10" name="MOSI/PB2" type="bidirectional"/>
        <pin num="11" name="MSIO/PB3" type="bidirectional"/>
        <pin num="12" name="PWM/PB7" type="bidirectional"/>
        <pin num="13" name="~{RESET}" type="input"/>
        <pin num="14" name="VCC" type="power_in"/>
        <pin num="15" name="GND" type="power_in"/>
        <pin num="16" name="XTAL2" type="output"/>
        <pin num="17" name="XTAL1" type="input"/>
        <pin num="18" name="SCL/PD0" type="bidirectional"/>
        <pin num="19" name="SDA/PD1" type="bidirectional"/>
        <pin num="20" name="RX1/PD2" type="bidirectional"/>
        <pin num="21" name="TX1/PD3" type="bidirectional"/>
        <pin num="22" name="XCK/PD5" type="bidirectional"/>
        <pin num="23" name="GND" type="passive"/>
        <pin num="24" name="AVCC" type="power_in"/>
        <pin num="25" name="ADC8/PD4" type="bidirectional"/>
        <pin num="26" name="ADC9/PWM/PD6" type="bidirectional"/>
        <pin num="27" name="ADC10/PWM/PD7" type="bidirectional"/>
        <pin num="28" name="ADC11/PB4" type="bidirectional"/>
        <pin num="29" name="ADC12/PWM/PB5" type="bidirectional"/>
        <pin num="30" name="ADC13/PWM/PB6" type="bidirectional"/>
        <pin num="31" name="PC6" type="bidirectional"/>
        <pin num="32" name="PC7" type="bidirectional"/>
        <pin num="33" name="~{HWB}/PE2" type="bidirectional"/>
        <pin num="34" name="VCC" type="passive"/>
        <pin num="35" name="GND" type="passive"/>
        <pin num="36" name="ADC7/PF7" type="bidirectional"/>
        <pin num="37" name="ADC6/PF6" type="bidirectional"/>
        <pin num="38" name="ADC5/PF5" type="bidirectional"/>
        <pin num="39" name="ADC4/PF4" type="bidirectional"/>
        <pin num="40" name="ADC1/PF1" type="bidirectional"/>
        <pin num="41" name="ADC0/PF0" type="bidirectional"/>
        <pin num="42" name="AREF" type="passive"/>
        <pin num="43" name="GND" type="passive"/>
        <pin num="44" name="AVCC" type="passive"/>
      </pins>
    </libpart>
    <libpart lib="basic_microcontroller" part="SPEJ110100">
      <description>DPDT Momentary Push Button Switch, PCB, 14V dc</description>
      <fields>
        <field name="Reference">S</field>
        <field name="Value">Pushbutton Switch</field>
        <field name="Footprint">SPEJ110100</field>
        <field name="Height">8</field>
        <field name="Mouser Part Number">688-SPEJ110100</field>
        <field name="Mouser Price/Stock">https://www.mouser.co.uk/ProductDetail/Alps-Alpine/SPEJ110100?qs=YMSFtX0bdJBg5hL%2FI29c%252BQ%3D%3D</field>
        <field name="Manufacturer_Name">ALPS Electric</field>
        <field name="Manufacturer_Part_Number">SPEJ110100</field>
      </fields>
      <pins>
        <pin num="1" name="COM_1" type="passive"/>
        <pin num="2" name="NO_1" type="passive"/>
        <pin num="3" name="NC_1" type="passive"/>
        <pin num="4" name="COM_2" type="passive"/>
        <pin num="5" name="NO_2" type="passive"/>
        <pin num="6" name="NC_2" type="passive"/>
      </pins>
    </libpart>
    <libpart lib="basic_microcontroller" part="Stemma">
      <description>Adafruit Accessories JST PH 4-pin Horizontal Connector (10-pack) - STEMMA</description>
      <docs>https://www.mouser.dk/datasheet/2/737/4389_C13924-001_CCP-W20-03-BK-SMT-R-A-1708610.pdf</docs>
      <fields>
        <field name="Reference">C</field>
        <field name="Value">Stemma</field>
        <field name="Footprint">4392</field>
        <field name="Datasheet">https://www.mouser.dk/datasheet/2/737/4389_C13924-001_CCP-W20-03-BK-SMT-R-A-1708610.pdf</field>
        <field name="Height">6.85</field>
        <field name="Mouser Part Number">485-4392</field>
        <field name="Mouser Price/Stock">https://www.mouser.co.uk/ProductDetail/Adafruit/4392?qs=xZ%2FP%252Ba9zWqbG2TKb%252Bnxciw%3D%3D</field>
        <field name="Manufacturer_Name">Adafruit</field>
        <field name="Manufacturer_Part_Number">4392</field>
      </fields>
      <pins>
        <pin num="1" name="1" type="passive"/>
        <pin num="2" name="2" type="passive"/>
        <pin num="3" name="3" type="passive"/>
        <pin num="4" name="4" type="passive"/>
        <pin num="MP1" name="MP1" type="passive"/>
        <pin num="MP2" name="MP2" type="passive"/>
      </pins>
    </libpart>
  </libparts>
  <libraries>
    <library logical="Connector">
      <uri>/usr/share/kicad/symbols//Connector.kicad_sym</uri>
    </library>
    <library logical="Device">
      <uri>/usr/share/kicad/symbols//Device.kicad_sym</uri>
    </library>
    <library logical="MCU_Microchip_ATmega">
      <uri>/usr/share/kicad/symbols//MCU_Microchip_ATmega.kicad_sym</uri>
    </library>
    <library logical="basic_microcontroller">
      <uri>/home/alex/PlaygroundCode/basic_microcontroller/ThirdParty/basic_microcontroller.kicad_sym</uri>
    </library>
  </libraries>
  <nets>
    <net code="1" name="+5V">
      <node ref="C4" pin="2" pintype="passive"/>
      <node ref="C5" pin="2" pintype="passive"/>
      <node ref="C6" pin="3" pinfunction="3" pintype="passive"/>
      <node ref="C7" pin="2" pintype="passive"/>
      <node ref="C8" pin="2" pintype="passive"/>
      <node ref="D27" pin="1" pinfunction="A" pintype="passive"/>
      <node ref="D28" pin="2" pinfunction="A" pintype="passive"/>
      <node ref="F1" pin="1" pintype="passive"/>
      <node ref="J2" pin="2" pinfunction="VCC" pintype="passive"/>
      <node ref="R3" pin="1" pintype="passive"/>
      <node ref="R36" pin="1" pintype="passive"/>
      <node ref="R37" pin="1" pintype="passive"/>
      <node ref="U1" pin="14" pinfunction="VCC" pintype="power_in"/>
      <node ref="U1" pin="2" pinfunction="UVCC" pintype="power_in"/>
      <node ref="U1" pin="24" pinfunction="AVCC" pintype="power_in"/>
      <node ref="U1" pin="34" pinfunction="VCC" pintype="passive"/>
      <node ref="U1" pin="44" pinfunction="AVCC" pintype="passive"/>
      <node ref="U1" pin="7" pinfunction="VBUS" pintype="input"/>
    </net>
    <net code="2" name="/AREF">
      <node ref="U1" pin="42" pinfunction="AREF" pintype="passive"/>
    </net>
    <net code="3" name="/LED_COL1">
      <node ref="R13" pin="2" pintype="passive"/>
      <node ref="R18" pin="2" pintype="passive"/>
      <node ref="R23" pin="2" pintype="passive"/>
      <node ref="R28" pin="2" pintype="passive"/>
      <node ref="R8" pin="2" pintype="passive"/>
      <node ref="U1" pin="20" pinfunction="RX1/PD2" pintype="bidirectional"/>
    </net>
    <net code="4" name="/LED_COL2">
      <node ref="R14" pin="2" pintype="passive"/>
      <node ref="R19" pin="2" pintype="passive"/>
      <node ref="R24" pin="2" pintype="passive"/>
      <node ref="R29" pin="2" pintype="passive"/>
      <node ref="R9" pin="2" pintype="passive"/>
      <node ref="U1" pin="21" pinfunction="TX1/PD3" pintype="bidirectional"/>
    </net>
    <net code="5" name="/LED_COL3">
      <node ref="R10" pin="2" pintype="passive"/>
      <node ref="R15" pin="2" pintype="passive"/>
      <node ref="R20" pin="2" pintype="passive"/>
      <node ref="R25" pin="2" pintype="passive"/>
      <node ref="R30" pin="2" pintype="passive"/>
      <node ref="U1" pin="25" pinfunction="ADC8/PD4" pintype="bidirectional"/>
    </net>
    <net code="6" name="/LED_COL4">
      <node ref="R11" pin="2" pintype="passive"/>
      <node ref="R16" pin="2" pintype="passive"/>
      <node ref="R21" pin="2" pintype="passive"/>
      <node ref="R26" pin="2" pintype="passive"/>
      <node ref="R31" pin="2" pintype="passive"/>
      <node ref="U1" pin="22" pinfunction="XCK/PD5" pintype="bidirectional"/>
    </net>
    <net code="7" name="/LED_COL5">
      <node ref="R12" pin="2" pintype="passive"/>
      <node ref="R17" pin="2" pintype="passive"/>
      <node ref="R22" pin="2" pintype="passive"/>
      <node ref="R27" pin="2" pintype="passive"/>
      <node ref="R32" pin="2" pintype="passive"/>
      <node ref="U1" pin="26" pinfunction="ADC9/PWM/PD6" pintype="bidirectional"/>
    </net>
    <net code="8" name="/LED_ROW1">
      <node ref="D2" pin="2" pinfunction="A" pintype="passive"/>
      <node ref="D3" pin="2" pinfunction="A" pintype="passive"/>
      <node ref="D4" pin="2" pinfunction="A" pintype="passive"/>
      <node ref="D5" pin="2" pinfunction="A" pintype="passive"/>
      <node ref="D6" pin="2" pinfunction="A" pintype="passive"/>
      <node ref="U1" pin="40" pinfunction="ADC1/PF1" pintype="bidirectional"/>
    </net>
    <net code="9" name="/LED_ROW2">
      <node ref="D10" pin="2" pinfunction="A" pintype="passive"/>
      <node ref="D11" pin="2" pinfunction="A" pintype="passive"/>
      <node ref="D7" pin="2" pinfunction="A" pintype="passive"/>
      <node ref="D8" pin="2" pinfunction="A" pintype="passive"/>
      <node ref="D9" pin="2" pinfunction="A" pintype="passive"/>
      <node ref="U1" pin="39" pinfunction="ADC4/PF4" pintype="bidirectional"/>
    </net>
    <net code="10" name="/LED_ROW3">
      <node ref="D12" pin="2" pinfunction="A" pintype="passive"/>
      <node ref="D13" pin="2" pinfunction="A" pintype="passive"/>
      <node ref="D14" pin="2" pinfunction="A" pintype="passive"/>
      <node ref="D15" pin="2" pinfunction="A" pintype="passive"/>
      <node ref="D16" pin="2" pinfunction="A" pintype="passive"/>
      <node ref="U1" pin="38" pinfunction="ADC5/PF5" pintype="bidirectional"/>
    </net>
    <net code="11" name="/LED_ROW4">
      <node ref="D17" pin="2" pinfunction="A" pintype="passive"/>
      <node ref="D18" pin="2" pinfunction="A" pintype="passive"/>
      <node ref="D19" pin="2" pinfunction="A" pintype="passive"/>
      <node ref="D20" pin="2" pinfunction="A" pintype="passive"/>
      <node ref="D21" pin="2" pinfunction="A" pintype="passive"/>
      <node ref="U1" pin="37" pinfunction="ADC6/PF6" pintype="bidirectional"/>
    </net>
    <net code="12" name="/LED_ROW5">
      <node ref="D22" pin="2" pinfunction="A" pintype="passive"/>
      <node ref="D23" pin="2" pinfunction="A" pintype="passive"/>
      <node ref="D24" pin="2" pinfunction="A" pintype="passive"/>
      <node ref="D25" pin="2" pinfunction="A" pintype="passive"/>
      <node ref="D26" pin="2" pinfunction="A" pintype="passive"/>
      <node ref="U1" pin="36" pinfunction="ADC7/PF7" pintype="bidirectional"/>
    </net>
    <net code="13" name="/MISO">
      <node ref="J2" pin="1" pinfunction="MISO" pintype="passive"/>
      <node ref="U1" pin="11" pinfunction="MSIO/PB3" pintype="bidirectional"/>
    </net>
    <net code="14" name="/MOSI">
      <node ref="J2" pin="4" pinfunction="MOSI" pintype="passive"/>
      <node ref="U1" pin="10" pinfunction="MOSI/PB2" pintype="bidirectional"/>
    </net>
    <net code="15" name="/RESET">
      <node ref="J2" pin="5" pinfunction="~{RST}" pintype="passive"/>
      <node ref="R3" pin="2" pintype="passive"/>
      <node ref="S1" pin="4" pinfunction="COM_2" pintype="passive"/>
      <node ref="S1" pin="6" pinfunction="NC_2" pintype="passive"/>
      <node ref="U1" pin="13" pinfunction="~{RESET}" pintype="input"/>
    </net>
    <net code="16" name="/SCK">
      <node ref="J2" pin="3" pinfunction="SCK" pintype="passive"/>
      <node ref="U1" pin="9" pinfunction="SCL/PB1" pintype="bidirectional"/>
    </net>
    <net code="17" name="/SCL">
      <node ref="C6" pin="1" pinfunction="1" pintype="passive"/>
      <node ref="R37" pin="2" pintype="passive"/>
      <node ref="U1" pin="18" pinfunction="SCL/PD0" pintype="bidirectional"/>
    </net>
    <net code="18" name="/SDA">
      <node ref="C6" pin="2" pinfunction="2" pintype="passive"/>
      <node ref="R36" pin="2" pintype="passive"/>
      <node ref="U1" pin="19" pinfunction="SDA/PD1" pintype="bidirectional"/>
    </net>
    <net code="19" name="/SS">
      <node ref="U1" pin="8" pinfunction="SS/PB0" pintype="bidirectional"/>
    </net>
    <net code="20" name="/TRI_LED_B">
      <node ref="R35" pin="1" pintype="passive"/>
      <node ref="U1" pin="12" pinfunction="PWM/PB7" pintype="bidirectional"/>
    </net>
    <net code="21" name="/TRI_LED_G">
      <node ref="R34" pin="1" pintype="passive"/>
      <node ref="U1" pin="30" pinfunction="ADC13/PWM/PB6" pintype="bidirectional"/>
    </net>
    <net code="22" name="/TRI_LED_R">
      <node ref="R33" pin="1" pintype="passive"/>
      <node ref="U1" pin="29" pinfunction="ADC12/PWM/PB5" pintype="bidirectional"/>
    </net>
    <net code="23" name="GND">
      <node ref="C1" pin="1" pintype="passive"/>
      <node ref="C2" pin="1" pintype="passive"/>
      <node ref="C3" pin="1" pintype="passive"/>
      <node ref="C4" pin="1" pintype="passive"/>
      <node ref="C5" pin="1" pintype="passive"/>
      <node ref="C6" pin="4" pinfunction="4" pintype="passive"/>
      <node ref="C6" pin="MP1" pinfunction="MP1" pintype="passive"/>
      <node ref="C6" pin="MP2" pinfunction="MP2" pintype="passive"/>
      <node ref="C7" pin="1" pintype="passive"/>
      <node ref="C8" pin="1" pintype="passive"/>
      <node ref="J1" pin="A1" pinfunction="GND" pintype="passive"/>
      <node ref="J1" pin="A12" pinfunction="GND" pintype="passive"/>
      <node ref="J1" pin="B1" pinfunction="GND" pintype="passive"/>
      <node ref="J1" pin="B12" pinfunction="GND" pintype="passive"/>
      <node ref="J2" pin="6" pinfunction="GND" pintype="passive"/>
      <node ref="J3" pin="2" pinfunction="Pin_2" pintype="passive"/>
      <node ref="R38" pin="2" pintype="passive"/>
      <node ref="R4" pin="1" pintype="passive"/>
      <node ref="R5" pin="2" pintype="passive"/>
      <node ref="R6" pin="2" pintype="passive"/>
      <node ref="R7" pin="2" pintype="passive"/>
      <node ref="S1" pin="1" pinfunction="COM_1" pintype="passive"/>
      <node ref="S1" pin="3" pinfunction="NC_1" pintype="passive"/>
      <node ref="U1" pin="15" pinfunction="GND" pintype="power_in"/>
      <node ref="U1" pin="23" pinfunction="GND" pintype="passive"/>
      <node ref="U1" pin="33" pinfunction="~{HWB}/PE2" pintype="bidirectional"/>
      <node ref="U1" pin="35" pinfunction="GND" pintype="passive"/>
      <node ref="U1" pin="43" pinfunction="GND" pintype="passive"/>
      <node ref="U1" pin="5" pinfunction="UGND" pintype="passive"/>
    </net>
    <net code="24" name="Net-(D1-A)">
      <node ref="D1" pin="2" pinfunction="A" pintype="passive"/>
      <node ref="U1" pin="1" pinfunction="PE6" pintype="bidirectional"/>
    </net>
    <net code="25" name="Net-(D1-K)">
      <node ref="D1" pin="1" pinfunction="K" pintype="passive"/>
      <node ref="R7" pin="1" pintype="passive"/>
    </net>
    <net code="26" name="Net-(D2-K)">
      <node ref="D2" pin="1" pinfunction="K" pintype="passive"/>
      <node ref="R8" pin="1" pintype="passive"/>
    </net>
    <net code="27" name="Net-(D3-K)">
      <node ref="D3" pin="1" pinfunction="K" pintype="passive"/>
      <node ref="R9" pin="1" pintype="passive"/>
    </net>
    <net code="28" name="Net-(D4-K)">
      <node ref="D4" pin="1" pinfunction="K" pintype="passive"/>
      <node ref="R10" pin="1" pintype="passive"/>
    </net>
    <net code="29" name="Net-(D5-K)">
      <node ref="D5" pin="1" pinfunction="K" pintype="passive"/>
      <node ref="R11" pin="1" pintype="passive"/>
    </net>
    <net code="30" name="Net-(D6-K)">
      <node ref="D6" pin="1" pinfunction="K" pintype="passive"/>
      <node ref="R12" pin="1" pintype="passive"/>
    </net>
    <net code="31" name="Net-(D7-K)">
      <node ref="D7" pin="1" pinfunction="K" pintype="passive"/>
      <node ref="R13" pin="1" pintype="passive"/>
    </net>
    <net code="32" name="Net-(D8-K)">
      <node ref="D8" pin="1" pinfunction="K" pintype="passive"/>
      <node ref="R14" pin="1" pintype="passive"/>
    </net>
    <net code="33" name="Net-(D9-K)">
      <node ref="D9" pin="1" pinfunction="K" pintype="passive"/>
      <node ref="R15" pin="1" pintype="passive"/>
    </net>
    <net code="34" name="Net-(D10-K)">
      <node ref="D10" pin="1" pinfunction="K" pintype="passive"/>
      <node ref="R16" pin="1" pintype="passive"/>
    </net>
    <net code="35" name="Net-(D11-K)">
      <node ref="D11" pin="1" pinfunction="K" pintype="passive"/>
      <node ref="R17" pin="1" pintype="passive"/>
    </net>
    <net code="36" name="Net-(D12-K)">
      <node ref="D12" pin="1" pinfunction="K" pintype="passive"/>
      <node ref="R18" pin="1" pintype="passive"/>
    </net>
    <net code="37" name="Net-(D13-K)">
      <node ref="D13" pin="1" pinfunction="K" pintype="passive"/>
      <node ref="R19" pin="1" pintype="passive"/>
    </net>
    <net code="38" name="Net-(D14-K)">
      <node ref="D14" pin="1" pinfunction="K" pintype="passive"/>
      <node ref="R20" pin="1" pintype="passive"/>
    </net>
    <net code="39" name="Net-(D15-K)">
      <node ref="D15" pin="1" pinfunction="K" pintype="passive"/>
      <node ref="R21" pin="1" pintype="passive"/>
    </net>
    <net code="40" name="Net-(D16-K)">
      <node ref="D16" pin="1" pinfunction="K" pintype="passive"/>
      <node ref="R22" pin="1" pintype="passive"/>
    </net>
    <net code="41" name="Net-(D17-K)">
      <node ref="D17" pin="1" pinfunction="K" pintype="passive"/>
      <node ref="R23" pin="1" pintype="passive"/>
    </net>
    <net code="42" name="Net-(D18-K)">
      <node ref="D18" pin="1" pinfunction="K" pintype="passive"/>
      <node ref="R24" pin="1" pintype="passive"/>
    </net>
    <net code="43" name="Net-(D19-K)">
      <node ref="D19" pin="1" pinfunction="K" pintype="passive"/>
      <node ref="R25" pin="1" pintype="passive"/>
    </net>
    <net code="44" name="Net-(D20-K)">
      <node ref="D20" pin="1" pinfunction="K" pintype="passive"/>
      <node ref="R26" pin="1" pintype="passive"/>
    </net>
    <net code="45" name="Net-(D21-K)">
      <node ref="D21" pin="1" pinfunction="K" pintype="passive"/>
      <node ref="R27" pin="1" pintype="passive"/>
    </net>
    <net code="46" name="Net-(D22-K)">
      <node ref="D22" pin="1" pinfunction="K" pintype="passive"/>
      <node ref="R28" pin="1" pintype="passive"/>
    </net>
    <net code="47" name="Net-(D23-K)">
      <node ref="D23" pin="1" pinfunction="K" pintype="passive"/>
      <node ref="R29" pin="1" pintype="passive"/>
    </net>
    <net code="48" name="Net-(D24-K)">
      <node ref="D24" pin="1" pinfunction="K" pintype="passive"/>
      <node ref="R30" pin="1" pintype="passive"/>
    </net>
    <net code="49" name="Net-(D25-K)">
      <node ref="D25" pin="1" pinfunction="K" pintype="passive"/>
      <node ref="R31" pin="1" pintype="passive"/>
    </net>
    <net code="50" name="Net-(D26-K)">
      <node ref="D26" pin="1" pinfunction="K" pintype="passive"/>
      <node ref="R32" pin="1" pintype="passive"/>
    </net>
    <net code="51" name="Net-(D27-BK)">
      <node ref="D27" pin="2" pinfunction="BK" pintype="passive"/>
      <node ref="R35" pin="2" pintype="passive"/>
    </net>
    <net code="52" name="Net-(D27-GK)">
      <node ref="D27" pin="4" pinfunction="GK" pintype="passive"/>
      <node ref="R34" pin="2" pintype="passive"/>
    </net>
    <net code="53" name="Net-(D27-RK)">
      <node ref="D27" pin="3" pinfunction="RK" pintype="passive"/>
      <node ref="R33" pin="2" pintype="passive"/>
    </net>
    <net code="54" name="Net-(D28-K)">
      <node ref="D28" pin="1" pinfunction="K" pintype="passive"/>
      <node ref="R38" pin="1" pintype="passive"/>
    </net>
    <net code="55" name="Net-(F1-Pad2)">
      <node ref="F1" pin="2" pintype="passive"/>
      <node ref="J1" pin="A4" pinfunction="VBUS" pintype="passive"/>
      <node ref="J1" pin="A9" pinfunction="VBUS" pintype="passive"/>
      <node ref="J1" pin="B4" pinfunction="VBUS" pintype="passive"/>
      <node ref="J1" pin="B9" pinfunction="VBUS" pintype="passive"/>
    </net>
    <net code="56" name="Net-(J1-CC1)">
      <node ref="J1" pin="A5" pinfunction="CC1" pintype="bidirectional"/>
      <node ref="R5" pin="1" pintype="passive"/>
    </net>
    <net code="57" name="Net-(J1-CC2)">
      <node ref="J1" pin="B5" pinfunction="CC2" pintype="bidirectional"/>
      <node ref="R6" pin="1" pintype="passive"/>
    </net>
    <net code="58" name="Net-(J1-D+-PadA6)">
      <node ref="J1" pin="A6" pinfunction="D+" pintype="bidirectional"/>
      <node ref="J1" pin="B6" pinfunction="D+" pintype="bidirectional"/>
      <node ref="R1" pin="1" pintype="passive"/>
    </net>
    <net code="59" name="Net-(J1-D--PadA7)">
      <node ref="J1" pin="A7" pinfunction="D-" pintype="bidirectional"/>
      <node ref="J1" pin="B7" pinfunction="D-" pintype="bidirectional"/>
      <node ref="R2" pin="1" pintype="passive"/>
    </net>
    <net code="60" name="Net-(J1-SHIELD)">
      <node ref="J1" pin="MH" pinfunction="SHIELD" pintype="passive"/>
      <node ref="R4" pin="2" pintype="passive"/>
    </net>
    <net code="61" name="Net-(J3-Pin_1)">
      <node ref="J3" pin="1" pinfunction="Pin_1" pintype="passive"/>
      <node ref="U1" pin="41" pinfunction="ADC0/PF0" pintype="bidirectional"/>
    </net>
    <net code="62" name="Net-(U1-D+)">
      <node ref="R1" pin="2" pintype="passive"/>
      <node ref="U1" pin="4" pinfunction="D+" pintype="bidirectional"/>
    </net>
    <net code="63" name="Net-(U1-D-)">
      <node ref="R2" pin="2" pintype="passive"/>
      <node ref="U1" pin="3" pinfunction="D-" pintype="bidirectional"/>
    </net>
    <net code="64" name="Net-(U1-UCAP)">
      <node ref="C3" pin="2" pintype="passive"/>
      <node ref="U1" pin="6" pinfunction="UCAP" pintype="passive"/>
    </net>
    <net code="65" name="Net-(U1-XTAL1)">
      <node ref="C1" pin="2" pintype="passive"/>
      <node ref="U1" pin="17" pinfunction="XTAL1" pintype="input"/>
      <node ref="Y1" pin="2" pinfunction="2" pintype="passive"/>
    </net>
    <net code="66" name="Net-(U1-XTAL2)">
      <node ref="C2" pin="2" pintype="passive"/>
      <node ref="U1" pin="16" pinfunction="XTAL2" pintype="output"/>
      <node ref="Y1" pin="1" pinfunction="1" pintype="passive"/>
    </net>
    <net code="67" name="unconnected-(J1-SBU1-PadA8)">
      <node ref="J1" pin="A8" pinfunction="SBU1" pintype="bidirectional+no_connect"/>
    </net>
    <net code="68" name="unconnected-(J1-SBU2-PadB8)">
      <node ref="J1" pin="B8" pinfunction="SBU2" pintype="bidirectional+no_connect"/>
    </net>
    <net code="69" name="unconnected-(S1-NO_1-Pad2)">
      <node ref="S1" pin="2" pinfunction="NO_1" pintype="passive+no_connect"/>
    </net>
    <net code="70" name="unconnected-(S1-NO_2-Pad5)">
      <node ref="S1" pin="5" pinfunction="NO_2" pintype="passive+no_connect"/>
    </net>
    <net code="71" name="unconnected-(U1-ADC10{slash}PWM{slash}PD7-Pad27)">
      <node ref="U1" pin="27" pinfunction="ADC10/PWM/PD7" pintype="bidirectional"/>
    </net>
    <net code="72" name="unconnected-(U1-ADC11{slash}PB4-Pad28)">
      <node ref="U1" pin="28" pinfunction="ADC11/PB4" pintype="bidirectional"/>
    </net>
    <net code="73" name="unconnected-(U1-PC6-Pad31)">
      <node ref="U1" pin="31" pinfunction="PC6" pintype="bidirectional+no_connect"/>
    </net>
    <net code="74" name="unconnected-(U1-PC7-Pad32)">
      <node ref="U1" pin="32" pinfunction="PC7" pintype="bidirectional+no_connect"/>
    </net>
  </nets>
</export>
